{
	"@PLURAL": "ends(1)#ends(range(2,4))#or(ends(range(5, 19)), ends(0))",
	"dearUser": "Sayın Kullanıcı!",
	"error": "Hata",
	"settings": "Ayarlar",
	"settings-2": "Terminal ayarları",
	"regionalSettings": "Bölge ayarları",
	"timezone": "Saat dilimi",
	"timezone-2": "Saat Dilimi",
	"language": "Dil",
	"skin-theme": "Tema",
	"ui-zoom": "Yakınlaştırma",
	"ui-zoom-2": "Ölçek",
	"investment": "Ticaret",
	"payout": "Ödeme",
	"options": "Seçenekler",
	"quote": "Kota",
	"time": "Zaman",
	"past": "Kapatılan",
	"active": "Açıldı",
	"value": "Değer",
	"add": "Yeni sekme",
	"add-new-chart": "Yeni çizelge ekle",
	"charts-arrangement": "Çizelge kareleri",
	"turbo-cap": "Turbo",
	"count-chart": "{{@count}} çizelge",
	"count-charts": "{{@count}} çizelge",
	"one-chart": "1 çizelge",
	"two-charts": "2 çizelge",
	"three-charts": "3 çizelge",
	"four-charts": "4 çizelge",
	"refill": "Depozito",
	"wallets-types": "Hesap türleri",
	"history": "Geçmiş",
	"cashbox": "Bankacılık",
	"education": "Eğitim",
	"promos": "Bonuslar",
	"trading-history": "Ticaret geçmişi",
	"section-under-construction": "Bu bölüm yapım aşamasındadır",
	"count-purchase": "{{@count}} ticaret",
	"count-purchases": "{{@count}} #{trades@trade?count}",
	"total-payout": "Toplam ödeme",
	"cancel": "İptal",
	"apply": "Uygula",
	"period": "Dönem",
	"fast-stochastic-period": "Hızlı çizgi nokta",
	"slow-stochastic-period": "Yavaş çizgi nokta",
	"fast-stochastic-line-color": "Hızlı çizgi rengi",
	"slow-stochastic-line-color": "Yavaş çizgi rengi",
	"fast-stochastic-line-thickness": "Hızlı çizgi kalınlığı",
	"line-thickness": "Çizgi kalınlığı",
	"line-color": "Çizgi Rengi",
	"line-offset": "Satır kaydırma",
	"top-line-thickness": "Üst çizgi kalınlığı",
	"mid-line-thickness": "Orta çizgi kalınlığı",
	"offset": "Ofset",
	"bottom-line-thickness": "Alt çizgi kalınlığı",
	"bottom-line-period": "Alt çizgi nokta",
	"top-line-color": "Üst çizgi rengi",
	"top-line-period": "Üst çizgi nokta",
	"mid-line-color": "Orta çizgi rengi",
	"mid-line-period": "Orta çizgi nokta",
	"bottom-line-color": "Alt çizgi rengi",
	"teeth-line-color": "Diş çizgisi rengi",
	"jaws-line-color": "Çene çizgisi rengi",
	"lips-line-color": "Dudak çizgisi rengi",
	"jaws-period": "Çene dönemi",
	"jaws-offset": "Çene ofseti",
	"teeth-period": "Diş dönemi",
	"teeth-offset": "Diş ofseti",
	"lips-period": "Dudak dönemi",
	"lips-offset": "Dudak ofseti",
	"indice-lines-position": "Belirteç çizgilerin konumu",
	"major-line-thickness": "Ana çizgi kalınlığı",
	"top-signal-line-thickness": "Üst sinyal çizgisi kalınlığı",
	"bottom-signal-line-thickness": "Alt sinyal çizgisi kalınlığı",
	"top-signal-line-color": "Üst sinyal çizgisi rengi",
	"bottom-signal-line-color": "Alt sinyal çizgisi rengi",
	"fast-stoch-color": "Hızlı olasılık rengi",
	"low-stoch-color": "Düşük olasılık rengi",
	"low-stoch-period": "Düşük olasılık dönemi",
	"fast-stoch-line-thickness": "Hızlı olasılık çizgileri kalınlığı",
	"low-stoch-line-thickness": "Düşük olasılık çizgileri kalınlığı",
	"small-period": "Küçük dönem",
	"big-period": "Büyük dönem",
	"small-period-width": "Küçük dönem kalınlığı",
	"big-period-width": "Büyük dönem kalınlığı",
	"signal-period-width": "Sinyal dönemi kalınlığı",
	"bars-color": "Çubuk rengi",
	"bars-color-maofmacd": "MACD/MA çubuğu kalınlığı",
	"smoothing-period": "Düzelme dönemi",
	"adx-minus-di-color": "-DI rengi",
	"adx-plus-di-color": "+DI rengi",
	"adx-line-color": "ADX çizgisi rengi",
	"sar-default-acceleration": "Varsayılan ivme",
	"acceleration-step": "İvemelenme adımı",
	"max-acceleration": "Maksimum ivme",
	"color": "Renk",
	"chart-type": "Çizelge türü",
	"chart-type-curve": "Eğri",
	"chart-type-curve-area": "Eğri alanı",
	"chart-type-candlesticks": "Şamdanlar",
	"chart-type-bars": "Çubuklar",
	"bet-sum": "Toplam",
	"chart-controls-income-caption": "Karlılık",
	"expiration-time": "Zaman aşımı süresi",
	"wallet-refilling": "Depozito",
	"real-wallet": "Gerçek",
	"demo-wallet": "Demo",
	"can-deduce-profit": "Karı çekebilirsiniz",
	"all-assets-available": "Tüm varlıklar kullanılabiliyor",
	"all-features-available": "Platformun tüm özelliklerini kullanın",
	"get-bonuses-from-the-platform": "Şirketten bonuslar alın",
	"participate-tournaments": "Yarışmaya katılın",
	"can-switch-wallet-any-time": "Hesaplar arasında dilediğiniz zaman geçiş yapabilirsiniz.",
	"cannot-deduce-profit": "Karı çekemezsiniz",
	"refill-wallet": "Depozito",
	"choose-wallet-type": "Hesap türü",
	"demo-wallet+wallet": "Demo hesabı",
	"real-wallet+wallet": "Gerçek hesap",
	"choose-bet": "Ticaret",
	"added-items": "Eklendi",
	"bollinger-lines": "Bollinger Bantları",
	"alli-gator": "Alli Timsah",
	"graphics-analysys-tools": "Analiz Araçları",
	"new-items": "Yeni",
	"line-segment": "Çizgi parçası",
	"ray": "Işın",
	"hori-line": "Yatay satır",
	"fibonacci-lines": "Fibonacci satırları",
	"andrews-fork": "Andrew dirgeni",
	"graphic-tools": "Grafik araçları",
	"time-period": "Zaman dilimi",
	"count-second": "{{@count}} saniye",
	"count-seconds": "{{@count}} saniye",
	"count-minute": "{{@count}} dakika",
	"count-minutes": "{{@count}} dakika",
	"count-hour": "{{@count}} saat",
	"count-hours": "{{@count}} saat",
	"lock-time": "Kilitlenme süresi",
	"user-profile": "Kullanıcı profili",
	"user-profile-heading": "Kullanıcı profili",
	"withdrawal": "Para Çekme",
	"support-service": "Destek",
	"payment-history": "Ödeme geçmişi",
	"exit": "Çıkış",
	"count-second-short": "{{@count}} sn",
	"count-seconds-short": "{{@count}} sn",
	"count-minute-short": "{{@count}} dk",
	"count-minutes-short": "{{@count}} dk",
	"count-hour-short": "{{@count}} st",
	"count-hours-short": "{{@count}} st",
	"count-day-short": "{{@count}} gn",
	"binary-cap": "İkili",
	"error-too-small-bet": "{{@sum}} değerine eşit bir bahiste bulunmak mümkün değildir, {{@currency}} para birimi için minimum bahis miktarı; {{@minbet}}",
	"error-too-big-bet": "{{@sum}} değerine eşit bir bahiste bulunmak mümkün değildir, {{@currency}} para birimi için maksimum bahis miktarı; {{@maxbet}}",
	"error-wrong-expiration": "{{@time}} yanlış zaman aşımı süresi",
	"not-enough-money": "Hesabınızdaki fonlar yetersiz.",
	"option-closed-head": "İşlem tamamlandı",
	"transaction-result": "{{@assetName}} sonuçları",
	"internet-connection-trouble": "Bağlantı sorunu",
	"lang-name-locale-en": "İngilizce",
	"lang-name-locale-ru": "Rusça",
	"lang-name-locale-de": "Almanca",
	"lang-name-locale-tr": "Türkçe",
	"lang-name-locale-vi": "Vietnamca",
	"lang-name-locale-uk": "Ukraynaca",
	"lang-name-locale-th": "Tay dili",
	"lang-name-locale-it": "İtalyanca",
	"lang-name-locale-pl": "Lehçe",
	"lang-name-chinese": "Çince (basitleştirilmiş)",
	"timezone-info": "(UTC+{{@offset}}) {{@country}}",
	"you-started-using-real-wallet": "Gerçek bir hesap kullanıyorsunuz.",
	"you-started-using-tment-wallet": "Yarışma hesabı kullanıyorsunuz.",
	"tournaments": "Yarışmalar",
	"currents": "Mevcut",
	"futures": "Gelecek",
	"archive": "Arşiv",
	"days": "Gün",
	"hours": "Saat",
	"minutes": "Dakika",
	"prize-fond": "Ödül",
	"participate-price": "Giriş ücreti",
	"prize-places": "Üst sıralar",
	"tournament-participants-count": "Katılımcılar",
	"no-tournament-description": "Yarışma açıklaması yok",
	"utc-info": "(UTC{{@offset}})",
	"begin-time": "Başlıyor",
	"deductions": "Kesinti",
	"reg-in-tournament-for": "{{@price}} ile yarışmaya katılın",
	"choose-tournament-to-see-info": "Lütfen bir yarışma seçin",
	"has-reged-in-tournament": "Kaydoldunuz",
	"wait-for-reg-in-tournament": "Kayıt talebi gönderildi",
	"prize-places-low": "{{@count}} En üst",
	"starting-balance": "Başlangıç bakiyesi",
	"min-deal-size": "Minimum ticaret tutarı",
	"max-deal-size": "Maksimum ticaret tutarı",
	"max-simultaneously-open-deals": "Açık ticaret limiti",
	"max-amount-of-open-deals": "Yatırım limiti",
	"available-options-types": "Kullanılabilir opsiyonlar",
	"tournament-option-type-turbo": "Turbo",
	"tournament-option-type-binary": "İkili",
	"tournament-option-type-both": "İkisi Birden",
	"tournament-winning-rules": "Turnuvanın sonunda en yüksek bakiyeye sahip tüccar kazanır.",
	"available-assets": "Kullanılabilir varlıklar",
	"available-options": "Kullanılabilir işlem türleri",
	"greeting": "Hoş geldiniz",
	"cashbox-plus-bonus": "bonus",
	"cashbox-input": "Depozito",
	"cashbox-output": "Para Çekme",
	"bonus-terms-of-use": "Kullanıcı bonus şartları",
	"enter-cashbox-input-value": "Depozito miktarı girin",
	"enter-cashbox-output-value": "Para çekme miktarı girin",
	"do-withdrawal": "Para Çekme",
	"amount-due": "Tutar",
	"will-recieve-to-account": "Şunu alırsınız;",
	"i-wanna-get-bonus": "Bonus alın",
	"enter-cashbox-card-type": "Ödeme yöntemi",
	"finish-time": "Bitiş",
	"top-users": "Lider Tablosu",
	"member": "Üye",
	"balance": "Bakiye",
	"prize": "Ödül",
	"hint-split-view-button": "Düzen",
	"hint-user-profile-button": "Kullanıcı menüsü",
	"hint-asset-stat": "Tüccarın seçimi",
	"hint-sound-button": "Ses",
	"hint-platform-time": "Platform zamanı",
	"hint-profitability": "Karlılık",
	"hint-payout": "Ödeme",
	"hint-real-acc": "Gerçek hesap",
	"hint-demo-acc": "Demo hesabı",
	"hint-tournament-acc": "Yarışma hesabı",
	"hint-settings": "Ayarlar",
	"hint-support": "Destek",
	"hint-graph-type": "Çizelge türü",
	"hint-candle-interval": "Mum aralığı",
	"hint-user-lines": "Grafik araçları",
	"hint-secondary-lines": "Belirteçler",
	"hint-centerize": "Mevcut fiyat",
	"hint-zoom-level": "Zaman Aralığı",
	"tournament": "Yarışma",
	"loading": "Yükleniyor",
	"you-are-in-tournament": "Katıldınız!",
	"repeat-tournament": "{{@price}} ile tekrar satın al",
	"unsupported-browser": "Ürün test aşamasındadır, şimdilik şu tarayıcılarda süreklililik garanti ediyoruz: Google Chrome, Opera ve Yandex Browser. Anlayışınız için teşekkürler!",
	"account-is-for-educ": "Bu sadece bir demo hesabı",
	"participate-in-demo-tments": "Demo yarışmaya katılın",
	"use-real-money": "Gerçek para ile ticaret yapın",
	"participate-tments-with-real-money": "Yarışmalara katılın ve ödüller kazanın",
	"native-deal-closed-body": "{{@assetName}} opsiyonu {{@closeTime}} zamanında kapandı. Kar; {{@incomeValue}}",
	"tournaments-rules": "Yarışma kuralları",
	"tournaments-rules-2": "Yarışmaya katılma kuralları.",
	"get-trade-exp": "Değerli ticari deneyim kazanın",
	"tment-begins-in": "Yarışmanın başlamasına kalan;",
	"tment-ends-in": "Yarışmanın bitimine kalan;",
	"tment-has-ended": "Yarışma sona erdi",
	"tment-just-ended": "\"{{@name}}\" az önce sona erdi",
	"tment-just-started": "\"{{@name}}\" az önce başladı",
	"tment-just-created": "\"{{@name}}\" az önce oluşturuldu",
	"read-more": "Daha fazla bilgi edinin",
	"history-is-empty": "Zamanı dolmuş teklifiniz yok",
	"tournaments-current-is-empty": "Aktif yarışma bulunmuyor. Lütfen haber akışımızı takip edin ve haber bültenlerini izleyin.",
	"tournaments-future-is-empty": "Planlanan bir yarışma bulunmuyor. Lütfen haber akışımızı takip edin ve haber bültenlerini izleyin.",
	"tournaments-ended-is-empty": "Bitmiş yarışma yok",
	"upper-indicator-line": "Üst belirteç çizgisi",
	"lower-indicator-line": "Alt belirteç çizgisi",
	"stoch-overbuy-value": "Aşırı Satın Alınmış",
	"stoch-overbuy-line-width": "Aşırı satın alınmış genişlik",
	"stoch-overbuy-line-color": "Aşırı satın alınmış renk",
	"stoch-oversell-value": "Aşırı Satılmış",
	"stoch-oversell-line-width": "Aşırı satılmış genişlik",
	"stoch-oversell-line-color": "Aşırı satılmış renk",
	"de1e3db3-5ed4-4941-aae4-59f3667cc3a3": "Bu değer geçerli değil",
	"889954f14a3839c141bd8d5102094fbb": "Bu değer zaten kullanılıyor",
	"bd79c0ab-ddba-46cc-a703-a7a4b08de310": "Bu değer geçerli bir eposta adresi değil",
	"bf447c1c-0266-4e10-9c6c-573df282e413": "Bu değer geçerli bir eposta adresi değil",
	"7da53a8b-56f3-4288-bb3e-ee9ede4ef9a1": "Bu değer geçerli bir eposta adresi değil",
	"c1051bb4-d103-4f74-8988-acbcafc7fdc3": "Bu alan gerekli.",
	"9ff3fdc4-b214-49db-8718-39c315e33d45": "Bu değer çok kısa. {{@min}} karakter ya da daha fazla olmalı.",
	"d94b19cc-114f-4f44-9cc4-4138e80a87b9": "Bu değer çok uzun. {{@limit}} karakter ya da daha az olmalı.",
	"478618a7-95ba-473d-9101-cabd45e49115": "Bu miktar belirtilene eşit olmalıdır {{@compared_value}}.",
	"4dba5f9c79ae34be5884e1a3c8c45e92": "Hatalı kullanıcı adı veya şifre",
	"3e5af93fb888b4aa77301a7603e113d5": "Yanlış şifre",
	"2d28afcb-e32e-45fb-a815-01c431a86a69": "Bu değer {{@limit}} ya da daha az olmalıdır",
	"76454e69-502c-46c5-9643-f447d837c4d5": "Bu değer {{@limit}} ya da daha fazla olmalıdır",
	"ad32d13f-c3d4-423b-909a-857b961eb720": "Bu değer sıfır olmamalıdır.",
	"8e179f1b-97aa-4560-a02f-2a8b42e49df7": "Seçtiğiniz değer geçerli bir seçim değil.",
	"853ff54c1a66d1a2379e0c46f8eb9ed4": "Geçersiz koşul {{@name}}",
	"3ac1d32eb3c54e11ef9ea474da816ad6": "{{@name}} gereksinimleri belirlenmeli",
	"661d3bc6c153e42a3658855010678cbd": "Bilinmeyen gereksinimler; {{@names}}",
	"51fd5caf0ad30e6acb3a75b8b7f6d060": "İşlem sürecinde olan bir talebin durumunu değiştiremezsiniz",
	"2d2ba82dd886ba3b69da804675842ff5": "Kötü ödeme yöntemi",
	"3c55616c0a7de9c064e6c2d86fa72bc2": "Geçersiz son tarih",
	"f029308ab5f1672de0b7615c4fa33386": "Varlık şu an için kapalı",
	"10cf6f3e2d6a3532b77d924868cbfa62": "Varlık şu an için kapalı",
	"64fc8bbac184ae9dab80c8f592d1a6f7": "Mevcut ticaret tutarı sınırını aşmış bulunuyorsunuz",
	"5561ccf1e94e6b9d88080bdbbcba1821": "Yetersiz bakiye",
	"f3a5b44d01097d966072b90187a16ec6": "Kullanıcı mevcut değil",
	"296ea5496bee3177c83ac27a1dc5bb10": "Yarışma bakiyesi başlangıç bakiyesinden az olmalıdır",
	"fc53df7c4944ebb53e8b3713126ae226": "Maksimum açık bahis sayısı {{@limit}} olabilir",
	"0f8e85ca21aa2e33752728cf5e843e35": "Mevcut ticaret tutarı sınırını aşmış bulunuyorsunuz",
	"cbce1334c90e82f44381abe99b98fe5c": "Açık opsiyon toplamı limiti aşıldı",
	"23bd9dbf-6b9b-41cd-a99e-4844bcf3077f": "Bu rumuz zaten kullanılıyor. Lütfen farklı bir rumuz seçin.",
	"promo-ends-in": "Bonusun bitimine kalan;",
	"your-promocode": "Promosyon kodunuz",
	"from-value-to-value": "{{@fromValue}} değerinden {{@toValue}} değerine",
	"deposit-sum": "Depozito toplamı",
	"bonus-sum": "Bonus",
	"promos-rules": "Bonus kuralları",
	"promos-rules-2": "Bonus kuralları",
	"participate-promo": "Bonusa katılın",
	"promo-has-ended": "Bonus sona erdi",
	"no-promos-description": "Bonus açıklaması yok",
	"promos-is-empty": "Kullanılabilir bonus yok",
	"first-launch-disclaimer-content": "Dikkat! Bir ticaret yapmak için Tek Tıklama yeterlidir. Onaya gerek yoktur.",
	"accept": "Kabul Et",
	"trading-session-closed": "Ticari oturum kapalı",
	"special-offer": "Özel teklif",
	"continue": "Devam",
	"seconds": "Saniye",
	"trading-sess-starts-in": "Ticari oturumun başlamasına kalan;",
	"trading-session-closed-info-0": "Dikkat!",
	"trading-session-closed-info-1": "Borsalar hafta sonları kapalıdır.",
	"trading-session-closed-info-2": "Platformumuzda Pazartesi 03:00 ila Cuma 00:00 arasında ticaret yapılabilir.",
	"trading-session-closed-info-3": "Piyasa verileri Thompson Reuters tarafından sağlanmaktadır.",
	"asset": "Varlık",
	"additional-info": "Ek bilgi",
	"fill-profile-to-continue": "Platforma çalışmaya devam etmek için ek bilgi verin",
	"fill-username-heading": "Sayın tüccar,",
	"fill-username-text": "Turnuvaya katılmak için sizi turnuva katılımcıları listesinde temsil edecek rumuzu girin. Bunu dilediğiniz zaman profil ayarlarınızdan değiştirebilirsiniz.",
	"fill-username-placeholder": "Lütfen rumuzunuzu girin",
	"save-and-continue": "Kaydet ve devam et",
	"profile-name": "İsim",
	"profile-surname": "Soyadı",
	"profile-telephone": "Telefon",
	"start-trading": "Ticarete başlayın",
	"personal-data-safety": "Kişisel verilerin güvenliğini garanti altında",
	"bonus": "Bonus",
	"new-bonus": "hesaba",
	"received-bonus": "Seçili para yatırma işlemiyle birlikte alacağınız",
	"received-bonus-value": "{{@bonus}} tutarında bir bonus",
	"mobile-received-bonus-value": "+ bonus {{@bonus}}",
	"expires-in": "Bitimine kalan;",
	"cannot-buy-option-try-later": "Bu ticaret açılamıyor, lütfen daha sonra tekrar deneyin.",
	"notifications$demo-option-limit": "Aynı anda 5'in üzerinde ticaret mi açmak istiyorsunuz? Gerçek bir hesap açın. Demo hesabınızı kullanmaya devam etmek için ticaretin tamamlanmasını bekleyin",
	"max-total-bet-limit-exceeded": "İzin verilen ticaret miktarını aştınız.\n {{@maxBet}} tutarında ticarete izin verilir",
	"chart-opens-in": "Varlığın kullanılabilir olmasına kalan süre:",
	"hint-activate-tment-wallet": "Yarışma hesabını kullanmaya başlamak için buraya basın",
	"largest-profit-banner-on-the-asset": "varlık üzerinde",
	"largest-profit-banner-button-trade-caption": "Ticaret",
	"largest-profit-banner-button-trade-caption-2": "Varlık ticaretine başlayın.",
	"largest-profit-banner-text": "Varlık ticareti için en iyi zaman",
	"largest-profit-banner-text-2": "Varlık ticareti için en uygun zaman",
	"largest-profit-height-profit": "Artan kârlılık",
	"largest-profit-height-profit-2": "Yüksek kârlılık",
	"offer-expires-in": "Teklifin kalan süresi:",
	"offer-expires-in-2": "Ticaretin bitmesine kalan süre:",
	"warning": "Uyarı",
	"banner-tech-works-info-caption": "Teknik güncellemeler",
	"banner-tech-works-info-content": "Her zaman ticaret platformumuzu geliştirmek için çalışıyoruz.\n Şu an platform güncelleniyor.\n Verdiğimiz rahatsızlıktan dolayı özür dileriz.",
	"confirm-email-content": "Lütfen e-posta adresinizi onaylayın. Onay bağlantısı olan e-postayı tekrar göndermek için aşağıdaki düğmeye tıklayın.",
	"confirm-email-caption": "Hesabı yeniden etkinleştirme",
	"reload": "Tekrar Yükle",
	"resend-confirmation": "Tekrar Gönder",
	"resend-confirmation-again": "Tekrar dene",
	"confirmation-mail-sent": "Gönderildi",
	"banner-not-enough-funds-for-tment": "Hesabınızda yeterli bakiye yok. Yarışmaya katılmak için lütfen hesabınıza bakiye yükleyin.",
	"tment-reenter-not-allowed": "Açık işlemler varken ek satın alma işlemi gerçekleştiremezsiniz.",
	"fill-profile-wrong-phone": "Geçersiz telefon numarası",
	"fill-profile-wrong-name": "Geçersiz isim",
	"fill-profile-wrong-surname": "Geçersiz soyadı",
	"fill-user-wrong-promocode": "Geçersiz promosyon kodu",
	"wrong-promocode-max-sum": "Maksimum depozito tutarı {{@sum}}",
	"wrong-promocode-min-sum": "Minimum toplam {{@sum}}",
	"wrong-withdrawal-min-sum": "Minimum toplam {{@sum}}",
	"wrong-withdrawal-max-sum": "Maksimum çekme tutarı {{@sum}}",
	"wrong-promocode-expired": "Süresi Doldu",
	"wrong-promocode-only-for-second-deposit": "Sadece ikinci ve sonraki depozitolar için geçerlidir",
	"wrong-promocode-only-for-first-deposit": "Sadece ilk depozito için geçerlidir",
	"wrong-promocode-used": "Promosyon kodu zaten kullanıldı",
	"fill-user-wrong-phone": "Geçersiz telefon numarası",
	"fill-user-wrong-card": "Geçersiz kart numarası",
	"fill-user-wrong-customer_purse": "Geçersiz hesap numarası",
	"fill-user-wrong-name": "Geçersiz isim",
	"fill-user-wrong-surname": "Geçersiz soyadı",
	"please-rotate-device": "Terminali kolayca kullanabilmek için cihazınızı yan çevirin.",
	"swipe-up-to-enter-fs": "Tam ekran moduna geçmek için yukarı kaydırın",
	"click-to-enter-fs": "Tam ekran moduna geçmek için ekrandaki herhangi bir yere dokunun",
	"reconnect": "Yeniden Bağlan",
	"reconnected": "Yeniden bağlanıldı!",
	"free-reg": "Ücretsiz kayıt",
	"investments": "ticaret",
	"investments_short": "yatırım.",
	"investment_short": "yatırım.",
	"buy-time": "Süre satın alın",
	"total-investment": "Toplam yatırım",
	"total-income": "Toplam ödeme",
	"result": "Sonuç",
	"ur-income-would-be": "Karınız",
	"create-account-for-free": "Ücretsiz hesap oluşturun",
	"resume-use-demo": "Demo modunda devam edin",
	"reg-request-message": "Web sitemizde ticaret yapmış olsaydınız şu ana kadar {{@income}} kazanmış olacaktınız. Daha fazla kayıp yaşamayın, ticarete başlayın!",
	"trade-without-restrictions": "Kısıtlamasız ticaret",
	"trade-without-restrictions-message": "Aynı anda 5'ten fazla ticaret açmak istiyorsanız ticari sınırı olmayan gerçek bir hesap açın. Demo hesabını kullanmaya devam etmek için lütfen teklifinizin süresinin dolmasını bekleyin.",
	"use-real-wallet": "Gerçek hesap",
	"support": "Destek",
	"search-asset": "Varlık ara",
	"error-sending-email-confirmation": "Posta gönderirken bir hata oluştu. Lütfen daha sonra tekrar deneyin.",
	"error-sending-email-confirmation-with-time": "{{@time}} dakika içinde size yeni bir e-posta gönderilebilir. Hesabınızı aktive etmek için lütfen e-postanızı kontrol edin veya destek hizmetimizle iletişime geçin.",
	"risk-free-trades": "Risksiz ticaretler",
	"count-trades-for-bet": "{{@count}} için ticaret oranı; {{@sum}}",
	"count-x-bet": "{{@count}}×{{@bet}}",
	"White": "Beyaz",
	"Red": "Kırmızı",
	"Pink": "Pembe",
	"Purple": "Mor",
	"Deep Purple": "Koyu Mor",
	"Indigo": "Çivit Mavisi",
	"Blue": "Mavi",
	"Cyan": "Deniz Mavisi",
	"Green": "Yeşil",
	"Light Green": "Açık Yeşil",
	"Lime": "Misket Yeşili",
	"Yellow": "Sarı",
	"Amber": "Bal Rengi",
	"Orange": "Turuncu",
	"tournament-accounts": "Turnuva hesapları",
	"activate-tournament-wallet": "Yarışma cüzdanını etkinleştirin",
	"deposit-using-agreements-header": "Bonus öğeler",
	"deposit-using-agreements-p1": "Bonus, tüccarların ticaret potansiyelini artırmak için şirket tarafından sunulan ek fondur.",
	"deposit-using-agreements-p2": "Para yatırırken, hesabınıza belirli bir miktar bonus para yatırılabilir, bonusun büyüklüğü depozitonuzun büyüklüğüyle ilişkilidir.",
	"deposit-using-agreements-p3": "Bonus, çekebileceğiniz para miktarını sınırlamaz, dilediğiniz zaman yatırdığınız para miktarıyla birlikte kârınızı çekebilirsiniz. Para çekerken, kazanılmayan tüm bonus paraya etkin değil durumu atanacağını ve hesabınızdan çekileceğini lütfen dikkate alın.",
	"choose-payment-method": "Para yatırma yöntemi seçin",
	"choose-payment-sum": "Depozito miktarı seçin",
	"plus-value-bonus": "+ {{@value}} bonus",
	"deposit-user-sum-value-caption": "Kendi miktarınızı mı belirlemek istiyorsunuz? Girdi alanını kullanın",
	"i-have-promocode": "Promosyon kodum var",
	"requisiste-name-phone": "Telefon",
	"no-bonus": "bonus yok",
	"refresh": "Yenile",
	"browser": "Tarayıcı",
	"make-a-deposit": "Bir depozito yatırın",
	"cashbox-withdrawal-info-0-header": "Hesabımdan nasıl para çekebilirim?",
	"cashbox-withdrawal-info-0-content": "Kullanılabilen seçenekler: banka kartı, Qiwi/Yandex Money/WebMoney e-cüzdanları. Mikro hesap sahiplerinin para çekebilmek için yalnızca bir etkin müraacatı olabilir.",
	"cashbox-withdrawal-info-1-header": "Hesaptan çekilebilecek maksimum para miktarı nedir?",
	"cashbox-withdrawal-info-1-content": "Minimum çekme miktarı — 300 ₽ veya 5 $ ya da 5 €. Tek bir işlem için maksimum çekme miktarı — 15.000 ₽ veya 200 $ ya da 200 €.",
	"cashbox-withdrawal-info-2-header": "15.000 ₽ veya 200 $ ya da 200, € üzerinde bir miktarı nasıl çekebilirim?",
	"cashbox-withdrawal-info-2-content": "Bu kısıtlama, hızlı hesap çekme işlemlerini önlemek için getirildi. Belirlenen limiti aşan miktarlar sadece uzun süre içinde çekilebilir. Daha yüksek bir miktar çekmek istiyorsanız paranızı 15.000 ₽ veya 200 $ ya da 200 €'luk çekimlere ayırabilirsiniz. Çekme talebi sayısı bakımından kısıtlama yoktur. Tek bir ödemede daha yüksek bir miktar çekmek isterseniz lütfen platform destek ekibiyle iletişime geçin. Hesabınız doğrulanmamışsa para çekme talebinizin işlenmesi üç iş gününü bulabilir. Günde birden fazla para çekme talebi gönderemezsiniz.",
	"cashbox-withdrawal-info-3-header": "Çekim işlemi ne kadar hızlıdır?",
	"cashbox-withdrawal-info-3-content-a": "Platformun finans departmanının iş saatleri sırasında gönderildiği ve platformun gerekliliklerine göre hesabınızın doğrulanmış olduğu farz edildiğinde, talebin işlenmesi bir saat sürer. ",
	"cashbox-withdrawal-info-3-content-b": "Finans departmanının çalışma saatleri pazartesiden cumaya, 10.00 ila 22.00 (GMT +2) arasındadır. Finans departmanının çalışma saatlerinin dışında veya tatilde para çekme talebi gönderdiyseniz talebiniz sonraki iş gününün başlangıcında işlenir. Hesabınız doğrulanmamışsa para çekme talebiniz üç iş günü içinde işlenir. Günde birden fazla para çekme talebi gönderemezsiniz.",
	"cashbox-withdrawal-info-4-header": "Bir çekim politikası",
	"cashbox-withdrawal-info-4-content-a": "Müşteri, talebinin gereğiyle işlenmesini sağlamak için \"Profil Ayarları\"nda istenen tüm verileri sağlamalıdır. Yanlış veya eksik veri girildiği belirlenirse para çekme talebiniz reddedilebilir veya ertelenebilir.",
	"cashbox-withdrawal-info-4-content-b": "Hesabınıza para eklemek için kullanılan aynı banka hesabına (veya aynı ödeme sistemine) para çekilir. İşlemi tamamlamak mümkün değilse, çevrimiçi sohbet başlatarak veya ssupport@binarium.com adresine bir destek talebi göndererek destek hizmetiyle iletişime geçmelisiniz.",
	"cashbox-withdrawal-info-5-header": "Para çekerken belge beyan etmem gerekir mi? Evetse, hangi belgeleri beyan etmeliyim?",
	"cashbox-withdrawal-info-5-content-a": "Çekme işlemlerinin hızlı olmasını sağlamak için lütfen \"Profil Ayarları\" bölümüne bütün kişisel verilerinizi sağlayın. Birden fazla banka kartı kullanıyorsanız veya ödeme bilgileri kayıt sırasında sağladığınız bilgilerle eşleşmiyorsa, tam izin sürecinden geçmeniz ve kartların gerçekten size ait olduğunu kanıtlamanız gerekir. Para, üçüncü taraf hesaplara çekilemez. ",
	"cashbox-withdrawal-info-5-content-b": "Doğrulama sürecini tamamlamak için sahibinin adı ve soyadı görünecek şekilde lütfen pasaportunuzu ve banka kartınızın ön yüzünü tarayıp support@binarium.com adresine gönderin. Kabartmalı bir kartınız varsa pasaportunuzun kopyasına ek olarak bu karttan Binarium hesabına bir işlemi gösteren banka işlem dekontunu da tarayıp göndermelisiniz. Kart sahibi ve ticaret hesabı verilerinin eşleşmemesi durumunda şirket, destekleyici ek belge isteme hakkını saklı tutar.",
	"cashbox-withdrawal-info-6-header": "Hangi şartlarda ikramiyeyi çekmek mümkündür?",
	"cashbox-withdrawal-info-6-content-a": "Bonus eklendikten hemen sonra çekilemez. Broker, ticaret fırsatlarınızı arttırmak için bu parayı hesabınıza bonus olarak ekler. Bonus parayı kullanarak kazandığınız faiz de bonus sayılır ve sadece gerekli ticaret cirosu elde edildikten sonra çekilebilir. Bonusu çekmek için hesaptaki bonus miktarının x40 cirosunu elde etmeniz gerekir. Para yatırma bonusu almadıysanız kaldıraç 50'ye çıkarılır, yani hesaptaki ciro, bonus x50'ye denk olmalıdır ve maksimum çekme miktarı, eklenen para yatırmama bonusu miktarını geçemez. Şirketin ücretsiz yarışmalarında kazanılan nakit ödülleri, yalnızca x40 ciro elde edildikten sonra çekim için uygun olan bonuslar olarak kabul edilir.",
	"cashbox-withdrawal-info-6-content-b": "Örneğin. Para yatırdığınızda, bonus olarak 150 $ aldınız. Kurallara göre, satın alınmış olan opsiyonların toplam değeri 30 x 150 = 4500 $ olmalıdır. Bu değere ulaşıldıktan sonra, bonus parayı çekebilirsiniz. Bu durumda, tüm kârlı ve kâr içermeyen işlemler göz önünde bulundurulur. Erken sonlandırılmış işlemler ciroya dahil değildir. Kârın çekilmesiyle ilgili herhangi bir kısıtlama bulunmamaktadır.",
	"cashbox-withdrawal-info-6-content-c": "Eğer ki depozitin bir kısmını çekecekseniz, miktara denk ikramiyenin bir kısmı otomatik olarak hesabınızdan çıkarılır.",
	"cashbox-withdrawal-info-6-content-d": "Sorunuz varsa lütfen Binarium destek ekibiyle iletişime geçin.",
	"cashbox-withdrawal-info-7-header": "Hesabımdan para çekme talebi oluşturamıyorum. Ne ters gidiyor olabilir?",
	"cashbox-withdrawal-info-7-content": "Öncelikle, \"Profil\" bölümünde, profil sayfanızda tüm kişisel bilgilerinizin listelenmiş olup olmadığını kontrol edin. Talebi gönderirken, bütün bilgilerin doğru girildiğinden emin olun. +, -, / gibi özel karakterler geçerli değildir. Girilen tüm bilgiler doğruysa ancak sorun devam ediyorsa lütfen çevrimiçi sohbet veya support@binarium.com adresinden müşteri destek ekibimizle iletişime geçin.",
	"deposit-info-1": "Bonus, tüccarların ticaret potansiyelini artırmak için şirket tarafından sunulan ek fondur",
	"deposit-info-2": "Para yatırırken, hesabınıza belirli bir miktar bonus para yatırılabilir, bonusun büyüklüğü depozitonuzun büyüklüğüyle ilişkilidir.",
	"deposit-info-3": "Bonus, çekebileceğiniz para miktarını kısıtlamaz, dilediğiniz zaman, yatırdığınız para miktarını ve kârınızı çekebilirsiniz. Para çekerken x40 cirolu ticaretlerde kullanılmayan tüm bonus paraya etkin değil durumu atanır ve hesabınızdan çekilir.",
	"withdrawal-heading": "Talebiniz, gönderildikten sonra 24 saat içinde işleme alınır.",
	"withdrawal-content": "Başvuru, şirketin finans departmanının çalışma saatlerinin dışında yapılmışsa sonraki iş gününde işleme alınır.",
	"withdrawal-restricted-heading": "Fon çekme talebi limiti aşıldı",
	"withdrawal-restricted-content": "Ne yazık ki, günde en fazla beş talep kabul edebiliyoruz. Yeni bir talep göndermek için daha önceden gönderdiğiniz talepleri iptal edin veya 24 saat içinde tekrar deneyin",
	"withdrawal-amount-caption": "Ödeme tutarı",
	"withdrawal-type-caption": "Para çekme yöntemi",
	"withdrawal-button-caption": "Para çekin",
	"requisite-name-card": "Kart numarası",
	"requisite-name-phone": "Telefon",
	"requisite-name-customer_purse": "Müşteri cüzdanı",
	"withdrawal-request-sent": "Talep sıraya kondu",
	"withdrawal-request-sent-extra-info": "Talebin durumunu \"İşlem Geçmişi\" kısmından takip edebilirsiniz.",
	"withdrawal-method-qiwi_ecom": "Qiwi",
	"withdrawal-method-qiwi": "Qiwi",
	"withdrawal-method-yandex_money_ecom": "Yandex Money",
	"withdrawal-method-webmoney_1gp": "WebMoney",
	"withdrawal-method-card": "Visa/Mastercard",
	"videohub": "Eğitim",
	"asset-type-all": "Tümü",
	"asset-type-currency": "Para Birimi",
	"asset-type-crypto": "Kripto",
	"asset-type-goods": "Mallar",
	"asset-type-countries": "Ülkeler",
	"asset-type-leaders": "Liderler",
	"cashbox-withdrawal-info": "Talebin işlenmesi biraz zaman alır. Finans departmanının talebi incelemesi iş saatleri sırasında gönderilmişse 24 saati bulabilir. Çekme talebinizin onaylanmasını beklerken bakiyenizi dondurmadığımızı söylemekten mutluluk duyarız. Bu şekilde, ticaret yapmaya devam edebilirsiniz.",
	"expiration-caption-16": "24 saat içerisinde",
	"trends": "Trendler",
	"show-chart": "Çizelgeyi göster",
	"hide-chart": "Çizelgeyi gizle",
	"trend-active": "Aktif",
	"trend-non-active": "Tümü",
	"trends-is-empty": "Trendler duraklatılıyor",
	"what-are-trends": "Trendler nelerdir?",
	"what-are-trends-advice-content": "Trendler kârlı potansiyeli (ve belirli bir fiyat yönü) olan bir varlığı kolayca bulmanıza yardımcı olan ve trend yönünde ticaret açılmasını sağlayan özel bir ticari araçtır.",
	"not-enough-money-for-trends-detailed": "Binarium, {{@balance}} üzerinde gerçek bakiyeye sahip müşterilerin kullanabileceği eşsiz bir ticaret aracına sahiptir. Umut verici fırsatlar:",
	"get-access-to-trends": "Trendlere erişim sahibi olun",
	"trends-features-one": "Piyasadaki tüm varlık trendlerini takip edin",
	"trends-features-two": "Trend göründüğünde trend yönünde anında ticaret açın",
	"month-0": "Ock",
	"month-1": "Şbt",
	"month-2": "Mrt",
	"month-3": "Nsn",
	"month-4": "Mys",
	"month-5": "Hzr",
	"month-6": "Tmz",
	"month-7": "Ağs",
	"month-8": "Eyl",
	"month-9": "Ekm",
	"month-10": "Ksm",
	"month-11": "Arl",
	"day-0": "Pzt",
	"day-1": "Slı",
	"day-2": "Çrş",
	"day-3": "Prş",
	"day-4": "Cum",
	"day-5": "Cmt",
	"day-6": "Pz",
	"trading-room": "Ticaret odası",
	"trading-room-entering-time": "Giriş zamanı",
	"trading-room-expiration": "Süre Sonu",
	"trading-room-strength": "Kuvvet",
	"trading-room-strike-price": "İşlem fiyatı",
	"trading-room-is-empty": "Uygun sinyal yok. Lütfen kısa süre sonra Ticaret Odasını tekrar ziyaret edin.",
	"demo-stats-banner-header-caption": "Mükemmel!",
	"demo-stats-banner-header-caption-2": "Tebrikler!",
	"demo-stats-banner-you-earned-on-demo": "Demo hesabı üzerinden para kazandınız.",
	"demo-stats-banner-total-deals-amount": "Toplam ticaret",
	"demo-stats-banner-successfull-deals-percentage": "Başarılı ticaretlerin yüzdesi",
	"demo-stats-banner-real-account-opening-request": "Gerçek bir hesap açarak kazandığınız geliri çekme imkanına sahip olacaksınız",
	"demo-stats-banner-open-real-account-button-caption": "Gerçek bir hesap açın",
	"demo-stats-banner-keep-trading-on-demo": "Bir demo hesabıyla ticaret yapmaya devam edin",
	"demo-stats-banner-you-have-done": "Şunu yerleştirdiniz:",
	"demo-stats-banner-you-have-trades-closed-in-a-row": "üst üste ticaretler",
	"demo-stats-banner-you-have-trades-closed-in-a-row-successfully": "üst üste kârlı ticaretler",
	"demo-stats-banner-earning-on-demo-account": "Demo hesabınızdaki kazançlar",
	"demo-stats-banner-closed-in-a-row-2": "başarılı işlemler",
	"tour-next-button-caption": "Devam",
	"tour-reading-duration-caption": "4 dakika boyunca okuma.",
	"tour-slides-steps-count": "{{@currentSlide}} / {{@totalSlidesCount}}. adım",
	"tour-slide-0-caption": "Binarium yatırım platformuna hoş geldiniz",
	"tour-slide-0-content": "Bu kısa gösterim, size yatırımın ve Binarium platformunun temel prensiplerini açıklar.",
	"tour-slide-0-content-1": "Platformda nasıl daha etkili şekilde yatırım yapabileceğinizi öğrenmek için tüm kartları okuyun.",
	"tour-slide-0-content-2": "Bu kısa gösterim, size yatırımın ve Binarium platformunun temel prensiplerini açıklar.",
	"tour-slide-0-content-3": "Ana menü soldadır. Örneğin, <span class=\"bold\">Banka</span> bölümünden hesabınızı yeniden doldurabilirsiniz. <span class=\"bold\">Ticaret odası</span> bölümünden de platformdaki en iyi tüccarları kullanarak ticaret siparişi verebilirsiniz!",
	"tour-slide-0-extra-info": "Platformda nasıl daha etkili şekilde yatırım yapabileceğinizi öğrenmek için tüm kartları okuyun.",
	"tour-slide-1-caption": "Platformda nasıl para kazanılır?",
	"tour-slide-1-content": "<span class=\"bold\">Yatırım platformu yatırım yapabilmenizi sağlar</span>. Bunları finansal varlıklara kısa süreli yatırımlar yaparak yapabilirsiniz: forex para birimi çiftleri, kripto para birimleri, emtia ve diğer finansal araçlar.",
	"tour-slide-2-caption": "Yatırım yapmanın arkasındaki temel prensip nedir?",
	"tour-slide-2-content-a": "<span class=\"bold\">Yatırım, belirli bir süre içinde finansal bir varlığın fiyatının nasıl değişeceğini tahmin etmektir.</span> Yatırımcılar <span class=\"green\">uzun</span> veya <span class=\"red\">kısa</span> yatırımlar yaparlar.",
	"tour-slide-2-content-b": "Tahmininiz doğru çıkarsa gelir elde edersiniz. Yanlışsa, yatırdığınız tüm fonları kaybedersiniz.",
	"tour-slide-3-caption": "Binarium platformuna nasıl yatırım yapılır?",
	"tour-slide-3-content": "Tahmin etmek istediğiniz <span class=\"bold\">bir varlık seçin</span>.",
	"tour-slide-4-caption": "Binarium platformuna nasıl yatırım yapılır?",
	"tour-slide-4-content": "<span class=\"bold\">Yatırımınızın boyutunu seçin.</span>",
	"tour-slide-5-caption": "Binarium platformuna nasıl yatırım yapılır?",
	"tour-slide-5-content": "Fiyatın <span class=\"green\">artacağını</span> veya <span class=\"red\">azalacağını<span class=\"red\"> tahmin ettikten sonra <span class=\"bold\">bir yatırım açın</span>. Yatırım kapanana kadar bekleyin.",
	"tour-slide-6-caption": "Binarium platformundaki yatırımlarınızda bol şans",
	"tour-slide-6-additional-caption": "Tahmininiz doğruysa kârınız otomatik olarak yatırım hesabınıza eklenir.",
	"tour-slide-6-a-trading-rules": "Yatırım koşulları",
	"tour-slide-6-a-card-0-caption": "Başarılı bir tahmin yapmaktan elde edeceğiniz gelir miktarı:",
	"tour-slide-6-a-card-0-content-1": "maksimum {{@maxProfit}}",
	"tour-slide-6-a-card-0-content-2": "başarılı bir tahmin yapmaktan elde edeceğiniz yatırım miktarı.",
	"tour-slide-6-a-card-1-caption": "yatırım için minimum para yatırma büyüklüğü.",
	"tour-slide-6-a-card-1-content": "en az {{@minWithdrawal}}",
	"tour-slide-6-a-card-2-caption": "fon çekmek için gereken ortalama süre:",
	"tour-slide-6-a-card-2-content": "30 dakika",
	"tour-slide-6-a-card-3-caption": "Yatırım yapmaya başlamak için gerçek bir hesaba fon ekleyin:",
	"tour-slide-6-a-card-3-button-caption": "Fon yatırın ve yatırım yapmaya başlayın",
	"tour-slide-6-a-dont-show-again": "Platform turunu kapat",
	"tour-slide-6-b-trading-rules": "Yatırım koşulları",
	"tour-slide-6-b-card-0-caption": "Başarılı bir tahmin yapmaktan elde edeceğiniz gelir miktarı:",
	"tour-slide-6-b-card-0-content": "Yatırım tutarınızın <span class=\"big\">en fazla %90</span>'ı.",
	"tour-slide-6-b-card-1-caption": "yatırım için minimum para yatırma büyüklüğü.",
	"tour-slide-6-b-card-1-content": "<span class=\"big\">{{@minWithdrawal}}</span>",
	"tour-slide-6-b-card-2-caption": "fon çekmek için gereken ortalama süre.",
	"tour-slide-6-b-card-2-content": "<span class=\"big\">30</span> dakika",
	"tour-slide-6-b-card-3-caption": "Demo hesabı kullanarak risk olmadan yatırım yapmayı öğrenin",
	"tour-slide-6-b-card-3-button-caption": "Demo hesabı kullanarak yatırım yapın",
	"tour-slide-6-b-dont-show-again": "Platform turunu kapat",
	"user-terms-caption": "Tek bir tıklamayla ticaret yapın",
	"what-is-trading-room": "Ticaret odası nedir?",
	"what-is-trading-room-advice-content": "Ticaret odası, tek bir tıklamayla platformun en iyi tüccarlarının işlemlerini kopyalamanıza izin veren kullanışlı bir araçtır. Bu araç sayesinde, ticaretinizin etkinliğini arttırıp zaman kazanabilirsiniz.",
	"not-enough-money-for-trading-room-detailed": "Ticaret odasını kullanarak Binarium platformunun en iyi tüccarlarıyla ticaret yapın ve para kazanın. Gerçek bakiyenizi {{@minBalance}} tutarına tamamlayın ve aşağıdaki avantajları elde edin:",
	"get-access-to-trading-room": "Ticaret odasına erişim",
	"have-access-to-trading-room": "\"Ticaret Odasına\" erişim sağlamak için yöneticinizle veya destek hizmetiyle iletişime geçin.",
	"trading-room-features-one": "Platformun en başarılı tüccarının işlemlerine göz atın",
	"trading-room-features-two": "İşlemleri kopyalayın ve kâr sağlayın",
	"trading-room_1-title": "Birlikte ticaret yapın",
	"trading-room_1-text": "Platformun en başarılı tüccarının işlemlerine göz atın.",
	"trading-room_2-title": "Başkalarının başarılı deneyimlerinin avantajını kullanın",
	"trading-room_2-text": "Diğer tüccarların davranışlarını kopyalayın ve kâr edin!",
	"trading-room_refill": "\"Ticaret odası\"na erişmek için bakiyenizi şu miktara yeniden doldurun:",
	"account_level": "Hesap seviyesi",
	"modal-confirm_title": "E-posta adresinizi onaylayın",
	"modal-confirm_text-1": "Kayıttan sonra size gelen mesajdaki onay bağlantısı.",
	"modal-confirm_text-2": "Onay bağlantısı içeren bir mesaj almadınız mı? Lütfen \"istenmeyen\" klasörünüzü kontrol edin. Bazen mesajlar oraya gider. Veya mesajı tekrar talep edin.",
	"modal-confirm_button": "Mesajı tekrar gönder",
	"modal-confirm_error-1-1": "{{@time}} dakika içinde size yeni bir e-posta gönderilebilir. Hesabınızı aktive etmek için lütfen e-postanızı kontrol edin veya destek hizmetimizle iletişime geçin ya da",
	"modal-confirm_error-1-2": "destek hizmetiyle iletişime geçin.",
	"modal-confirm_support": "Destek hizmetiyle iletişime geçin",
	"timer_days": "gün",
	"timer_hours": "saat",
	"timer_minutes": "dakika",
	"timer_seconds": "saniye",
	"tournament_button": "Yarışmaya katılın",
	"modal-oneclick_title": "Tek bir tıklamayla ticaret yapın",
	"modal-oneclick_text": "Platformda tek bir tıklamayla ticaret açabileceğinizi lütfen unutmayın. Ek bir onay yoktur.",
	"modal-oneclick_button": "Kabul et ve devam et",
	"modal-tbalance_title": "Hesabınızı yeniden doldurun",
	"modal-tbalance_text": "Hesabınızda yeterli para yok. Yarışmaya katılmak için lütfen hesabınızı yeniden doldurun.",
	"modal-tbalance_button": "Para yatırın",
	"modal-tech_title": "Yakında döneceğiz!",
	"modal-tech_text-1": "Sürekli olarak ticaret platformumuzu geliştirmeye çalışıyoruz. Şu anda güncelleme yapılıyor. Verdiğimiz rahatsızlıktan dolayı özür dileriz.",
	"modal-tech_text-2": "Çalışmanın bitmesine kalan süre:",
	"modal-tech_button": "Devam",
	"modal-session_title": "Dikkat",
	"modal-session_text-1": "Borsalar hafta sonları kapalıdır.",
	"modal-session_text-2": "Ticaret platformuna",
	"modal-session_text-3": "pazartesi 3.00 ve cuma 12.00 saatleri arasında erişim sağlanabilir.",
	"modal-session_text-4": "Ticaret oturumunuzun başlamasına kalan süre:",
	"modal-session_button": "Devam",
	"modal-tn_title": "Hoş geldiniz",
	"modal-tn_text-1": "Yarışmanın sonunda en yüksek bakiyeye sahip tüccar kazanır.",
	"modal-tn_text-2": "Kullanılabilir varlıklar:",
	"modal-tn_text-3": "Kullanılabilir işlem türleri:",
	"modal-tn_button": "Başlat",
	"modal-nickname_title": "Rumuz seçin",
	"modal-nickname_text": "Yarışmaya katılmak için sizi yarışma katılımcıları listesinde temsil edecek rumuzu girin. Bunu dilediğiniz zaman profil ayarlarınızdan değiştirebilirsiniz.",
	"modal-nickname_button": "Kaydet ve devam et",
	"modal-profile_title": "Ek bilgi",
	"modal-profile_text": "Platformda çalışmaya devam etmek için lütfen ek bilgi sağlayın.",
	"modal-profile_name": "Ad",
	"modal-profile_surname": "Soyad",
	"modal-profile_phone": "Kod ile birlikte telefon numarası",
	"modal-profile_button": "Ticarete başlayın",
	"modal-profile_aside": "Kişisel verilerinizin güvenliği garanti altında.",
	"form-error_required": "Bu alan gerekli.",
	"form-error_name-short": "Ad çok kısa.",
	"form-error_name-format": "Geçersiz ad formatı",
	"form-error_surname-short": "Soyadı çok kısa.",
	"form-error_surname-format": "Geçersiz soyadı formatı.",
	"form-error_phone-format": "Geçersiz telefon numarası formatı",
	"srv-err_asset-is-disabled": "Varlık devre dışı bırakıldı",
	"srv-err_asset-is-disabled-for-this-tournament": "Bu turnuva için varlık devre dışı bırakıldı",
	"srv-err_binary-is-disabled-for-this-tournament": "Bu turnuva için varlık devre dışı bırakıldı",
	"srv-err_turbo-is-disabled-for-this-tournament": "Bu turnuva için varlık devre dışı bırakıldı",
	"tournament@btn.paid-participate": "Giriş ücreti",
	"tournament@info.paid": "Ücretli turnuva",
	"faq@title": "Sorular ve cevaplar",
	"faq@g0": "Genel",
	"faq@g1": "Hesap",
	"faq@g2": "Finans",
	"faq@g3": "Ticaret",
	"faq@c0q0": "Platform demo hesabı sunuyor mu?",
	"faq@c0a0": "<p>Kayıttan hemen sonra bir ticaret hesabı (demo hesabı) alırsınız. Bu hesap, eğitim ve öğretim amaçlıdır. Bu hesaptan para çekemezsiniz. Gerçek ve demo hesaplarınız arasında ticaret terminalinde geçiş yaparak aynı anda iki hesapta birden ticaret yapabilirsiniz.<br> Demo hesabınıza fon eklemek için lütfen platformdaki hesabınızdan çıkış yapıp tekrar giriş yapın.</p>",
	"faq@c0q1": "Binarium ile nasıl çalışmaya başlayabilirim?",
	"faq@c0a1": "<p>Piyasada çalışmanın temel prensiplerine vâkıfsanız ve ikili opsiyonların ticaretini biliyorsanız, yapmanız gereken tek şey hesabınızı tamamlamanız ve ticarete başlamanız. Minimum mevduat oranı 5$/5€ veya 1500 rubledir. Eğer ki yeteneklerinize güvenmiyorsanız, demo hesap kullanarak alıştırma yapın ve eğitim materyallerimize göz atmayı ihmal etmeyin.</p>",
	"faq@c0q2": "Ticarete başlamadan önce herhangi bir belge imzalamam gerekiyor mu?",
	"faq@c0a2": "<p> Herhangi bir şey imzalamanız gerekmiyor. Kayıt esnasında müşteri sözleşmemizi onaylıyorsunuz. </p>",
	"faq@c0q3": "Bazı ülkelerle çalışmayla ilgili herhangi bir kısıtlama var mı?",
	"faq@c0a3": "<p>Yalnızca 2 ülkenin müşterileri hizmetlerimizden faydalanamaz - ABD ve İsrail. Bu ülkelerin müşterileri sitemize kayıt olamaz ve ticaret yapamaz. </p>",
	"faq@c0q4": "Ticaret yapmak için özel bir yazılım indirmeme gerek var mı?",
	"faq@c0a4": "<p>Hayır. Sadece binarium.com web sitesindeki terminalin web arayüzü yoluyla ticaret yapabilirsiniz. İnternet bağlantısı olan herhangi bir bilgisayardan ticaret yapabilirsiniz. Bunu yapmak için önce kayıt olmanız, sonra da kullanıcı adı ve şifrenizi girmeniz gerekir.<br>Akıllı telefondan ticaret yapmak için Binarium Android uygulamasını indirmeniz gerekir.</p>",
	"faq@c0q5": "İkili opsiyon nedir?",
	"faq@c0a5": "<p>Bu, bir varlığın fiyatında artış veya düşüş için bir işlem açabilmenizi sağlayan bir borsa aracıdır. Tüm riskler ve kârlar, işlem sonuçlanmadan önce bilinir. Platformda iki tür işlem açabilirsiniz - turbo (en fazla 5 dakika süreli kısa süreli işlemler) ve ikili (5 dakika ila 3 ay süreli, orta veya uzun süreli pozisyonlar).</p>",
	"faq@c0q6": "Süre sonu nedir?",
	"faq@c0a6": "<p>Kapanış zamanı aynı zamanda sona erme süresi olarak da bilinir. ticari işlemin kapanış sürecini gösteren zamandır. İşlem sonuçlarıyla, tüccar ya daha öncesine kabul etmiş olduğu bir ödeme alır veya hiçbir şey almaz. Hepsi tüccarın tahminlerinin gerçekleşmesine bağlıdır.</p>",
	"faq@c0q7": "Kapanış fiyatı nedir?",
	"faq@c0a7": "<p>Kapanış fiyatı, varlığın pozisyonun süresi sona erdiğindeki fiyatıdır.</p>",
	"faq@c0q8": "Teklif hangi şartlarda kârlı olur?",
	"faq@c0a8": "<p>Tahmininizin doğru çıkması durumunda kâr edersiniz. Örneğin, fiyatın artacağını tahmin ettiniz (ALMA pozisyonu açtınız) - bu durumda, pozisyonun süresi dolduğunda varlığın fiyatı teklif açıldığında olduğundan daha yüksekse kâr hesabınıza aktarılır.</p>",
	"faq@c0q9": "Destek hizmetinizden bir geri arama talep edebilir miyim?",
	"faq@c0a9": "<p>Evet, bir geri arama talebi mesajı yazın ve e-posta adresimize <a href=\"mailto:support@binarium.com\">support@binarium.com</a> veya <a class=\"open-chat-button\">canlı sohbete</a> gönderin. Destek hizmeti ekibi genelde bir iş saati içinde size geri dönüş yapar.</p>",
	"faq@c1q0": "Nasıl kayıt olabilirim?",
	"faq@c1a0": "<p>Tek yapmanız gereken sitemizin ana sayfasına yer alan hızlı kayıt formunu doldurmanız. </p>",
	"faq@c1q1": "Kayıt olmak için hesabıma yükleme yapmam gerekiyor mu?",
	"faq@c1a1": "<p>Hayır, kayıt işlemi ücretsizdir. Yalnızca gerçek bir hesap üzerinden ticarete başlarken hesabınıza yükleme yapmanız gerekmektir. Bundan önce, demo hesap kullanarak alıştırma yapabilirsiniz. </p>",
	"faq@c1q2": "İş için hangi para birimi kullanılabilir?",
	"faq@c1a2": "<p>Kayıt esnasında kullanıma uygun 3 para biriminden 1 tanesini seçebilirsiniz - dolar / euro / ruble. Hesabınızın para birimini değiştiremeyeceğinizi hatırlatırız, o yüzden seçiminizi bilinçli yapın. </p>",
	"faq@c1q3": "Hangi hesaba yükleme yapma yöntemleri mevcut?",
	"faq@c1a3": "<p>Binarium, müşterilerinin hesaplarına banka kartlarını (VISA/Mastercard/Mir), elektronik ödeme sistemlerini (Kiwi, Yandex.Money, Neteller, WebMoney ve AlfaClick) veya kripto para birimlerini (Bitcoin, Ethereum, Litecoin ve Ripple) kullanarak fon ekleyebilmelerini sağlar.</p>",
	"faq@c1q4": "Hesabıma yükleme yapmak ne kadar sürer?",
	"faq@c1a4": "<p>Hesabınıza yükleme anında yapılır. Para Binarium hesabına yatırıldığı an, ticari platform üzerinde veya şahsi hesabınızda hemen görüntülenebilir. </p>",
	"faq@c1q5": "Para yatıramıyorum, bu sorunu nasıl çözebilirim?",
	"faq@c1a5": "<p>Bu sorunun bir çok sebebi olabilir. Durumunuzu anlayabilmemiz açısından, lütfen müşteri hizmetlerine talep gönderin. Bunu <a href=\"mailto:support@binarium.com\">support@binarium.com</a> adresine başvuru yaparak veya sorunu <a class=\"open-chat-button\">canlı sohbet</a> kısmına bildirerek sağlayabiliriniz.</p>",
	"faq@c1q6": "Hesabımdan nasıl para çekebilirim?",
	"faq@c1a6": "<p>Qiwi, Yandex.Money, WebMoney, Neteller, Bitcoin, Ethereum, Litecoin ve Ripple ödeme sistemlerini kullanarak banka kartınıza veya hesabınıza para aktarabilirsiniz.</p>",
	"faq@c1q7": "Hesaptan para çekimi için bir başvuru oluşturamıyorum, Sorun ne olabilir?",
	"faq@c1a7": "<p>Öncelikle, profilinizde tüm şahsi bilgilerinizin listelenmiş olup olmadığından emin olun, kontrol edebilmek için ''Profil'' kısmına gidin, tekrar ediyoruz, tüm bilgilerinizin başvuru talebinde bulunulmadan önce doğru girmiş olduğunuzdan emin olun, +,-,/ vb. sembolleri geçersizdir. Eğer ki tüm bilgiler doğru girilmişse, fakat sorun devam ediyorsa, lütfen canlı sohbet veya <a href=\"mailto:support@binarium.com\">support@binarium</a> vasıtasıyla müşteri hizmetleri ile iletişime geçin. </p>",
	"faq@c1q8": "Hesap türüne sahip olmam gerekir mi? Öyleyse bunu nasıl yapabilirim?",
	"faq@c1a8": "<p>Hesap türün tüm tamamlanan para yatırma miktarına ve gerçek fonların ticaret hacmine dayalıdır. Atanan hesap türünün süresi dolmaz.<br> Hesap türleri hakkında daha fazla bilgi için <a href=\"/main/cashbox/account-types\">Hesap Türlerini</a> inceleyin</p>",
	"faq@c2q0": "En az para yatırma tutarı ne kadardır?",
	"faq@c2a0": "<p>Minimum para yatırma tutarını 300 ruble veya 5$/5€ olarak belirledik. Bundan daha küçük miktarda para yatırmanız mümkün değildir.</p>",
	"faq@c2q1": "Maksimum para yatırmada bir limit var mıdır?",
	"faq@c2a1": "<p>Böyle bir limitimiz yok. Ancak, bir ödeme için müşteri tarafından bir hesaba 600 000 ruble / 10 000 $ / 10 000 € tutarından daha fazla para yatırılamaz. Yine de bu miktarda işlemleri sınırsız olarak peş peşe tekrarlayabilirsiniz.</p>",
	"faq@c2q2": "Hesaptan çekilebilecek maksimum para miktarı nedir?",
	"faq@c2a2": "<p>Minimum çekim tutarı 300 ruble veya 5 $ / 5 € kadardır. Her çekim işlemi için maksimum miktar 15 000 ruble yada 250 $ / 252 € olabilir.</p>",
	"faq@c2q3": "15 000 ruble veya 250 $ / 250 € tutarından fazlasını nasıl çekebilirim?",
	"faq@c2a3": "<p>Bu limit hızlı ödeme yapılabilmesi için belirlenmiştir çünkü bunun üzerindeki tutarları çekmesi daha zordur. Daha fazla çekim yapmanız gerekirse çekim miktarlarını 15 000 / 250 $ / 250 € tutarlık parçalara ayırabilirsiniz. Çekim sayısı hesap türüne bağlıdır. Bir ödemede yüklü çekimler yapabilmek için lütfen şirket desteği ile iletişime geçin</p>",
	"faq@c2q4": "Hesaba para eklemenin/çekmenin ek ücreti var mıdır?",
	"faq@c2a4": "<p>Ödemelerden komisyon veya ücret almıyoruz. Ve müşterilerimizin yatırım hesabına para yatırma/çekme işlemleri için gereken ödeme sistemleri ücretini de karşılıyoruz.<br><br>Ancak, para çekmek için başvurduysanız ve yatırım cironuz (tüm yatırımlarınızın toplamı) yatırılan paranın iki katını geçmiyorsa, para çekmek için talep edilen çekim tutarının %10'u tutarındaki ödeme sistemi ücretlerini karşılamama hakkına sahiptir.</p>",
	"faq@c2q5": "Ödeme çekim işlemi ne kadar hızlıdır?",
	"faq@c2a5": "<p>Bir başvurunun işlenmesi için gereken süre bir saattir. Bu süre, başvuru platformun finans departmanının çalışma saatleri sırasında gönderilirse ve hesabınız platform gerekliliklerine göre doğrulanırsa geçerlidir. <br>Finans departmanının çalışma saatleri 10.00 - 22.00'dir (GMT +2). Fon çekme başvurusu finans departmanının çalışma saatleri dışında veya hafta sonlarında gerçekleşirse başvuru bir sonraki çalışma gününün başlangıcında işlenir.<br>Hesabınız doğrulanmamışsa fon çekme başvurunuzun işlenmesi 3 çalışma gününü bulabilir. Aynı anda günlük birden fazla fon çekme başvurusu gönderemezsiniz.</p>",
	"faq@c2q6": "Bir çekim politikası.",
	"faq@c2a6": "<p>Başvurunun dosyalanması ve şirket tarafından işleme alınması için müşterinin <a href=\"/main/profile\">Profil</a> kısmında istenen tüm verileri doldurması gerekir. Veriler yanlış veya eksikse çekim işlemi reddedilebilir ya da gecikebilir. Şirket, hesabın yüklendiği aynı havuzdan çekim yapar. Bu şekilde bir işlem mümkün değilse <a class=\"open-chat-button\">çevrimiçi sohbet</a> ile veya <a href=\"mailto:support@binarium.com\">support@binarium.com</a> adresi aracılığıyla teknik destekle iletişime geçin.</p>",
	"faq@c2q7": "Çekim işlemi sırasında belge beyan etmem gerekir mi? Evetse, hangileri beyan etmeliyim?",
	"faq@c2a7": "<p>Hızlı para çekme işlemi gerçekleştirmek için lütfen \"Profil Ayarları\" bölümündeki tüm kişisel verilerinizi doldurun. Birden fazla kredi kartı kullanıyorsanız ya da ödeme bilgileriniz kayıt sırasında sağladıklarınızla örtüşmüyorsa tam izin prosedüründen geçmeniz ve kartların gerçekten size ait olduğunu kanıtlamanız gerekir. Üçüncü taraf bir hesaba fon aktaramazsınız.</p><p>Bir VISA/Mastercard/Maestro banka kartı kullanarak hesabınıza fon eklemişseniz:</p><p>Doğrulama prosedürünü tamamlamak için lütfen şu bilgileri id@binarium.com adresine gönderin:</p><ul> <li>Kredi kartınızın ön ve arka yüzünü tarayın veya yüksek kalitede fotoğraflarını çekin. Şu bilgiler taranmış belgede açık bir şekilde görülebilir olmalıdır:</li><li> <ul> <li>Kart numaranızın ilk 6 ve son 4 hanesi, örneğin: 530403XXXXXX1111. Ortadaki rakamları gizleyebilirsiniz;</li><li>Kart sahibinin adı ve soyadı;</li><li>Kartın son kullanma tarihi;</li><li>Kartın arka kısmı imzalanmış olmalıdır;</li><li>CVV kodu kapatılmış olmalıdır;</li></ul> </li><li>Kart sahibinin pasaportunun iki sayfası taranmalı veya yüksek kaliteli fotoğrafı çekilmelidir. Tüm bilgiler açık bir şekilde görülebilir olmalıdır. Lütfen taranmış belgenin veya pasaport sayfalarının fotoğraflarının hiçbir kısmını gizlemeyin veya düzenleme yapmayın.</li><li>Binarium platformunuz için para eklemeyi gösteren resmi bir banka dekontu. İnternet bankacılığı mobil uygulamanızdan indirilen dekontlar kabul edilmez.</li></ul><p>Elektronik bir ödeme sistemi (Qiwi, Webmoney, Yandex.Money, Alfa-bank, Neteller) kullanarak para eklediyseniz:</p><p>Doğrulama prosedürünü tamamlamak için lütfen şu bilgileri id@binarium.com adresine gönderin:</p><ul> <li>Ticaret hesabının sahibinin pasaportunun taranmış belgesi. Tüm bilgiler açık bir şekilde görülebilir olmalıdır ve hiçbir kısmı kapatılmamalıdır.</li><li>Binarium platformu için para ekleme işleminin göründüğü, çevrimiçi ödeme sisteminden dekont (ekran görüntüsü). Belge platform ödemesinin yapıldığı ay içindeki tüm işlemleri göstermelidir.</li></ul>",
	"faq@c2q8": "Neden çekim talebim tamamlanmasına rağmen kart / e-cüzdanımda para yok?",
	"faq@c2a8": "<p>Para çekimi zaman aralığı seçili ödeme sistemine bağlı olarak değişmektedir.</p><ul><li>Bir banka kartına gönderim yapılması durumunda. Paranın gönderilme süreci bir kaç adımdan oluşmaktadır, ve dekontun basımı kartınızın ait olduğu bankanın işlem sürecine bağlıdır. Paranın banka kartına transferi bir kaç iş günü sürebilir.</li><li> E-cüzdana para gönderimi yapılması durumunda. Para onay işleminin finans departmanı tarafından gerçekleştirilmesinin ardından bir saat içerisinde e-cüzdana yatar.</li></ul><p>Paranın yatırılma sürecinde gecikmelere sebep olabilecek çeşitli forsmajör durumlar olabilir (örneğin, işlem merkezinde teknik sorunlar veya e-cüzdan sistemindeki sorunlar). Böyle durumlarda lütfen anlayışlı olun, çünkü bu şirketin suçu değil. Eğer ki para kartınız / e-cüzdanınıza belirtilen zaman içerisinde yatmadıysa, çekim talebinizin durumuyla ilgili bilgi almak için lütfen <a class=\"open-chat-button\">müşteri hizmetleri</a> ile iletişime geçin.</p>",
	"faq@c2q9": "Bonus fon nedir?",
	"faq@c2a9": "<p>İkramiye şirketin sizin ticaret potansiyelinizi arttırmak amacıyla hesabınıza yatırdığı mutlak para miktarıdır. İkramiye miktarı hesabınızın durumuna ve yatırılan paraların dökümüne bağlı olarak hesaplanır.</p><p>Şu ikramiyeleri sağlıyoruz:</p><ul><li> Hoş geldin ikramiyesi - yeni müşterilerin yatırdıkları ilk depozitoya verilen ikramiye;</li><li>Çeşitli şirket etkinliklerine katılım doğrultusunda verilen ikramiye;</li><li>ticari faaliyetlerin sigortası - sınırlı sayıdaki faaliyet için zararın karşılanması;</li><li>Herhangi bir yarışmanın parçası olan ödül fonu ikramiyesi, ödül fonu aldıkları derecelerine göre katılımcılar arasında dağıtılır.</li></ul><p>İkramiye miktarı ve alım koşulları bahsi geçen her durum için farklıdır. Şirketin herhangi bir koşulda müşteri sözleşmesini ihlal etmeniz durumunda sizi verilen ikramiyeden men edebilir.</p><p>Bir hesaba yükleme yaparken, ikramiye alımını reddedebilirsiniz, Eğer ki depozito yatırma işlemi ödeme sistemi sınırlandırmaları neticesinde parçalar halinde yürütüldüyse, lütfen tüm ikramiyeyi almak için <a class=\"open-chat-button\">destek</a> ile iletişime geçin. </p>",
	"faq@c2q10": "Mevduat sigortası / ticaret sigortası veya sigorta seçeneği nedir?",
	"faq@c2a10": "<p>Müşteriye sınırlı sayıda sigortalı ticari işlem sağlanabilir. Şirket böyle durumlarda zaiyatı karşılama sorumluluğunu üstlenir.</p><p>Bir takım kurallar mevcut:</p><ul><li> Yalnızca ilk işlemler/opsiyonlar sigortalıdır.</li><li> Bir işlemin değeri depozitonun %33'den daha fazla olamaz;</li><li>Toplam sigorta miktarı depozito miktarını geçemez.</li></ul><p>Eğer ki tüccar, örneğin, beş sigortalı işlem aldıysa, ve eğer kapatıldıktan sonra hesaptaki miktar ticaretten önceki miktardan azsa, broker farkı karşılamaktadır, böyle bir durumda tazminat miktarı ikramiye olarak ele alınır ve standart ikramiyelerle aynı kurallara tabidir.</p><p>Eğer ki sigortanın sağladığı şartları ihlal etmediyseniz, <a class=\"open-chat-button\">destek</a> ile tazminatınızı alabilmek için iletişime geçin.</p>",
	"faq@c2q11": "Hangi şartlarda ikramiyeyi çekmek mümkündür?",
	"faq@c2a11": "<p>Bonus, alındıktan hemen sonra çekilebilir. Broker, yatırım fırsatlarınızı arttırmak için bu parayı bakiyenize ek olarak verir. Bonus fonlarla kazanılan para da bonustur ve yalnızca gerekli yatırım getirisi elde edildikten sonra çekilebilir. Bonusu çekmek için hesaptaki bonus miktarının x40 getirisini elde etmeniz gerekir. Depozito bonus almamanız durumunda kaldıraç 50'ye çıkarılır, yani hesaptaki getiri bonus x50'ye eşdeğer olmalıdır ve maksimum çekim tutarı depozito olmama bonusuna eklenen tutarı geçemez. Şirketin ücretsiz turnuvalarından gelen para ödülleri bonustur ve x40 getiriyi elde ettikten sonra çekilebilir.</p><p>Örnek. Para yatırdığınızda bonus olarak 150 $ alırsınız. Kurallara göre satın alınan opsiyonların toplam değerinin 40 x 150 = 6000 $ olması gerekir. Bu tutar elde edildikten sonra bonus fonları çekebilirsiniz. Bu durumda hem kâr edilebilen hem kâr edilemeyen işlemler dikkate alınır. Açılış fiyatında kapanan teklifler geçerli değildir. Ayrıca, yatırım platformunda çifte teklif (Martingale) stratejisinin yasak olduğunu ve bu strateji yardımıyla yapılan tekliflerin bonus hesaplanırken dikkate alınmadığını, ayrıca şirketin kararıyla iptal edilebileceğini lütfen unutmayın. Kârın çekilmesi konusunda herhangi bir kısıtlama yoktur.</p><p></p><p>Depozitonun bir kısmını çekecekseniz bonus hesabınızdan otomatik olarak düşülür.</p><p>Bonus belirlenirken, aktif olarak alınan bonusların miktarının %5'unu geçmeyen bir tutar, yatırım hacmine yönelik olarak tek bir işlemin ne kadar olduğu göz önünde bulundurularak hesaba katılır. Örneğin, 100 USD'lik bonus alırsanız, bonus belirlenirken işlem başına en fazla 5 USD göz önünde bulundurulur. 20 USD'lik bir işlem başlatırsanız, yatırım hacminin bir parçası olarak 5 USD hesaplanır.</p><p>Anlaşılmayan bir kısım varsa Binarium müşteri desteğiyle iletişime geçebilirsiniz.</p>",
	"faq@c2q12": "Risksiz anlaşma nedir?",
	"faq@c2a12": "<p>Özel promosyon kodları veya teklifleri kullanarak yükleme yaptığınızda, hesabınıza belirli bir sayıda işlem eklenir ve yatırdığınız parayı riske etmeden bunu açabilirsiniz (işlemlerin sayısı ve tutarı teklifin veya promosyon kodunun tanımında belirtilmektedir). </p><p>Risksiz bir anlaşma açtığınızda, fonlar bakiyenizden düşülmez, tüm kâr hesabınıza bonus olarak eklenir. </p><p> Risksiz anlaşmalar aldığınızda, anlaşmaların toplam tutarına denk bir tutar bakiyenize yatırılır ve bonus olarak hesabınıza eklenir. Örneğin, hesabınıza 100 $ eklendi ve her biri 10 $ tutarında 3 risksiz anlaşma aldınız. Bu durumda, asıl bakiyenizden 30 $ yatırılır ve bonus olarak hesabınıza eklenir.</p><p>Risksiz anlaşmalar için bonus alma koşulları, normal bonuslara uygulanan koşullara benzerdir.<p>",
	"faq@c3q0": "Maksimum ticaret miktarı nedir?",
	"faq@c3a0": "<p>Kurallara göre bir işleme 10,000$/10,000€/600,000 rubleden fazlası yatırılamaz. Ancak, işlem sayısı sınırsızdır.</p>",
	"faq@c3q1": "Minimum ticaret miktarı nedir?",
	"faq@c3a1": "<p>İşlemlerin hacmi 1$/1€/60 ruble tutarından az olamaz.</p>",
	"faq@c3q2": "Nasıl ticaret yaparım?",
	"faq@c3a2": "<p>Bir varlık, süre sonu periyodu ve işlem boyutu seçip fiyatın hareket yönünü belirleyin. Varlığın fiyatının artacağını düşünüyorsanız yukarıyı gösteren yeşil oka tıklayın. Fiyatın düşeceğini düşünüyorsanız aşağıyı gösteren kırmızı düğmeye tıklayın.<br>Binarium platformunun ikiye katlayan işlemler için Martingale stratejisinin sistematik kullanımını yasakladığını lütfen dikkate alın. Bu kuralın ihlali işlemlerin iptal edilmesine ve ticaret hesabınızın dondurulmasına neden olabilir.</p>",
	"faq@c3q3": "Hesap hareketleri geçmişi nerede sergileniyor?",
	"faq@c3a3": "<p>Ticaret geçmişini kişisel hesabınızda ve (<a href=\"/main/deal-history\">\"Ticaret Geçmişi\"</a>kısmından) ticaret platformunun \"Geçmiş\" kısmından görebilirsiniz.</p>",
	"faq@c3q4": "Peki ya kar marjı?",
	"faq@c3a4": "<p>Tahmin gerçekleşirse kar, işlemin %90'ına ulaşır.</p>",
	"faq@c3q5": "Açılan işlemlerimi nasıl takip edebilirim?",
	"faq@c3a5": "<p>İşlemler varlık çizelgesinde görüntülenir. Aynı anda farklı 4 grafik ile çalışabilirsiniz.</p>",
	"faq@c3q6": "Binarium platformunda ne zaman yatırım yapılabilir?",
	"faq@c3a6": "<p>Tüm mal varlıklarının ticareti Pazartesi ila Cuma günleri arasında mümkündür. Hafta sonları sadece kripto para birimi, LATAM, GSMI endeksleri ve OTC varlıklarıyla ticaret yapabilirsiniz.</p>",
	"faq@c3q7": "Her varlık için ticaret saatlerini nerede bulabilirim?",
	"faq@c3a7": "<p>Ticaret saatleri \"Mal varlığı kataloğu\"nda bulunur.</p>",
	"faq@c3q8": "Ticaret eğitimi veriyor musunuz?",
	"faq@c3a8": "<p>Evet, Binarium yeni başlayanların için alıştırma sunmaktadır, ücretsiz bilgi ''Eğitim'' bölümünde yer alır. Firma'nın analistlerinden biriyle bireysel eğitim yapabilmek mümkündür. Şahsi eğitmene ihtiyacınızı varsa, <a class=\"open-chat-button\">canlı sohbet</a> kısmından veya telefon vasıtasıyla detayları konuşmanız gerekmektedir.</p>",
	"faq@c3q9": "İşlemler nasıl denetleniyor?",
	"faq@c3a9": "<p>İşlem geçmişinde gördüğünüz tüm bilgiler broker sisteminde saklanır. Açılış ve kapanış işlemi sırasındaki varlığım tam fiyatını, varlığın ismi ile saniyesi içerisinde işlemin açılış/kapanış süresini içerir. </p><p>Tüccarın şüpheye düştüğü durumlarda broker, teklif verene teklifin yeniden değerlendirilmesi için bir talep gönderir. Bu durumda, doğrulama süreci başvurunun ardından 3 günden fazla süremez. Müşteri, doğrulama sonuçlarını Binarium'a ulaşmasının hemen ardından alır.</p>",
	"faq@c3q10": "Teklifler neden FOREX teklifleri ve diğer kaynaklarla uyuşmuyor?",
	"faq@c3a10": "<p>Varyansın sebepleri:</p><ul><li>Forex Teklif ve Sor ücretini görüntüler, bu sırada Binarium ortalama fiyatı gösterirken, ki bu fiyat (Teklif+Sor)/2 formülüyle hesaplanır;</li><li>Kotasyonlar farklı kaynaklardan gelir ve ufak farklılıklar gösterebilir;</li><li>Kotasyon hasılatı zamanında ufak bir farklılık kurlarda farklılıklara sebep olabilir (tam olarak virgülden sonra 4.-5. hane).</li></ul><p> Kayıt yaptırarak Binarium'dan gelen kurların öncelikli olduğunu kabul etmiş oluyorsunuz. Bu kurlar diğer kaynaklardan gelen kotasyonlarla örtüşmeyebilir, Üçüncü taraf kaynakları kotasyon uzlaşması için kullanılamazlar, yalnızca yardımcı araç olarak kullanılabilirler.<p>",
	"menu@faq": "SSS",
	"cashbox@no-bonus": "Bonus alma",
	"wallet-menu@real-title": "Gerçek fon",
	"wallet-menu@bonus-title": "Bonus fon",
	"wallet-menu@wager-title": "Bonus çekmek için ciro",
	"wallet-menu@wager-link": "Bonuslar hakkında daha fazla bilgi alın",
	"modal-bonus@title": "Bonus fonlarını kullanıyorsunuz",
	"modal-bonus@text": "Ticaret boyutu kullanılabilir gerçek fonlarınızı aşıyor. Yani bu işlemi açtığınızda bonus fonlarınız kullanılacak:",
	"modal-bonus@deal-size": "Ticaret boyutu",
	"modal-bonus@real-size": "Gerçek fon",
	"modal-bonus@bonus-size": "Bonus fon",
	"modal-bonus@info": "Ticaretin bir parçası olarak alınan tüm fonlar bonus hesabınıza eklenecek.",
	"modal-bonus@faq": "Bonus fonu kullanım kuralları",
	"modal-bonus@btn-cancel": "İptal et",
	"modal-bonus@btn-continue": "Kabul et ve devam et",
	"modal-bonus@disable": "Artık bu mesajı gösterme",
	"trends@restrict-title": "Hesabınızdaki fonlar yetersiz",
	"trends@restrict-text": "Trendler bölümünün kilidini açmak için hesap bakiyenizin en az şu kadar olması gerekiyor:"
}