{
	"@PLURAL": "ends(1)#ends(range(2,4))#or(ends(range(5, 19)), ends(0))",
	"dearUser": "¡Querido/a usuario/a!",
	"error": "Error",
	"settings": "Ajustes",
	"settings-2": "Ajustes del terminal",
	"regionalSettings": "Ajustes de región",
	"timezone": "Huso horario",
	"timezone-2": "Zona horaria",
	"language": "Idioma",
	"skin-theme": "Tema",
	"ui-zoom": "Zoom",
	"ui-zoom-2": "Escala",
	"investment": "Operar",
	"payout": "Pago",
	"options": "Opciones",
	"quote": "Cotización",
	"time": "Hora",
	"past": "Expirado",
	"active": "Abierto",
	"value": "Valor",
	"add": "Nueva pestaña",
	"add-new-chart": "Agregar gráfico nuevo",
	"charts-arrangement": "Cuadro de gráficos",
	"turbo-cap": "Turbo",
	"count-chart": "{{@count}} gráfico",
	"count-charts": "{{@count}} gráficos",
	"one-chart": "1 gráfico",
	"two-charts": "2 gráficos",
	"three-charts": "3 gráficos",
	"four-charts": "4 gráficos",
	"refill": "Depósito",
	"history": "Historial",
	"cashbox": "Banca",
	"education": "Educación",
	"promos": "Bonos",
	"trading-history": "Historial de trading",
	"section-under-construction": "Esta sección está en construcción",
	"count-purchase": "{{@count}} operaciones",
	"count-purchases": "{{@count}} #{trades@trade?count}",
	"total-payout": "Pago total",
	"cancel": "Cancelar",
	"apply": "Aplicar",
	"period": "Período",
	"line-thickness": "Grosor de la línea",
	"line-color": "Color de la línea",
	"line-offset": "Cambio de la línea",
	"top-line-thickness": "Grosor de la línea superior",
	"mid-line-thickness": "Grosor de la línea del medio",
	"offset": "Desplazamiento",
	"bottom-line-thickness": "Grosor de la línea inferior",
	"bottom-line-period": "Período de la línea inferior",
	"top-line-color": "Color de la línea superior",
	"top-line-period": "Período de la línea superior",
	"mid-line-color": "Color de la línea del medio",
	"mid-line-period": "Período de la línea del medio",
	"bottom-line-color": "Color de la línea inferior",
	"teeth-line-color": "Color de la línea de dientes",
	"jaws-line-color": "Color de la línea de la mandíbula",
	"lips-line-color": "Color de la línea de los labios",
	"jaws-period": "Período de la mandíbula",
	"jaws-offset": "Compensación de la mandíbula",
	"teeth-period": "Período de los dientes",
	"teeth-offset": "Compensación de los dientes",
	"lips-period": "Período de los labios",
	"lips-offset": "Compensación de los labios",
	"indice-lines-position": "Posición de líneas de indicación",
	"major-line-thickness": "Grosor de la línea más grande",
	"top-signal-line-thickness": "Grosor de la línea de señal superior",
	"bottom-signal-line-thickness": "Grosor de la línea de señal inferior",
	"top-signal-line-color": "Color de la línea de señal superior",
	"bottom-signal-line-color": "Color de la línea de señal inferior",
	"fast-stoch-color": "Color del estocástico rápido",
	"low-stoch-color": "Color del estocástico bajo",
	"low-stoch-period": "Período del estocástico bajo",
	"fast-stoch-line-thickness": "Grosor de la línea del estocástico rápido",
	"low-stoch-line-thickness": "Grosor de la línea del estocástico bajo",
	"small-period": "Punto pequeño",
	"big-period": "Punto grande",
	"small-period-width": "Ancho del punto pequeño",
	"big-period-width": "Ancho del punto grande",
	"signal-period-width": "Ancho del punto de señal",
	"bars-color": "Color de la barra",
	"bars-color-maofmacd": "MA del color de la barra MACD",
	"smoothing-period": "Período de suavizado",
	"adx-minus-di-color": "Color -DI",
	"adx-plus-di-color": "Color +DI",
	"adx-line-color": "Color de la línea ADX",
	"sar-default-acceleration": "Aceleración por defecto",
	"acceleration-step": "Paso de aceleración",
	"max-acceleration": "Aceleración máxima",
	"color": "Color",
	"chart-type": "Tipo de gráfico",
	"chart-type-curve": "Curva",
	"chart-type-curve-area": "Área de curva",
	"chart-type-candlesticks": "Gráfico de velas",
	"chart-type-bars": "Barras",
	"bet-sum": "Importe",
	"chart-controls-income-caption": "Rentabilidad",
	"expiration-time": "Hora de caducidad",
	"wallet-refilling": "Depósito",
	"real-wallet": "Real",
	"demo-wallet": "Demostración",
	"can-deduce-profit": "Puede retirar la ganancia",
	"all-assets-available": "Todos los activos están disponibles",
	"all-features-available": "Todas las funciones de la plataforma",
	"get-bonuses-from-the-platform": "Obtenga bonificaciones de la empresa",
	"participate-tournaments": "Participe en concursos",
	"can-switch-wallet-any-time": "Puede cambiar de cuenta en cualquier momento.",
	"cannot-deduce-profit": "No puede retirar la ganancia",
	"refill-wallet": "Depósito",
	"choose-wallet-type": "Tipo de cuenta",
	"demo-wallet+wallet": "Cuenta de demostración",
	"real-wallet+wallet": "Cuenta real",
	"choose-bet": "Operar",
	"added-items": "Añadidos",
	"bollinger-lines": "Bandas de Bollinger",
	"alli-gator": "Alli Gator",
	"graphics-analysys-tools": "Herramientas de análisis",
	"new-items": "Nuevo",
	"line-segment": "Segmento de línea",
	"ray": "Rayo",
	"hori-line": "Línea horizontal",
	"fibonacci-lines": "Líneas de Fibonacci",
	"andrews-fork": "Tridente de Andrews",
	"graphic-tools": "Herramientas gráficas",
	"time-period": "Período de tiempo",
	"count-second": "{{@count}} segundo",
	"count-seconds": "{{@count}} segundos",
	"count-minute": "{{@count}} minuto",
	"count-minutes": "{{@count}} minutos",
	"count-hour": "{{@count}} hora",
	"count-hours": "{{@count}} horas",
	"lock-time": "Hora de bloqueo",
	"user-profile": "Perfil de usuario",
	"user-profile-heading": "Perfil de usuario",
	"withdrawal": "Retiro",
	"support-service": "Soporte",
	"payment-history": "Historial de pagos",
	"exit": "Cerrar la sesión",
	"count-second-short": "{{@count}} s",
	"count-minute-short": "{{@count}} m",
	"count-hour-short": "{{@count}} h",
	"count-day-short": "{{@count}} d",
	"binary-cap": "Binarios",
	"error-too-small-bet": "Es imposible hacer una apuesta igual a {{@sum}}, la apuesta mínima para la moneda {{@currency}} es {{@minbet}}",
	"error-too-big-bet": "Es imposible hacer una apuesta igual a {{@sum}}, la apuesta máxima para la moneda {{@currency}} es {{@maxbet}}",
	"error-wrong-expiration": "Hora de caducidad incorrecta {{@time}}",
	"not-enough-money": "No tiene fondos suficientes en su cuenta.",
	"option-closed-head": "Transacción completada",
	"transaction-result": "Resultado para {{@assetName}}",
	"internet-connection-trouble": "Problema de conexión",
	"lang-name-locale-en": "Inglés",
	"lang-name-locale-ru": "Ruso",
	"lang-name-locale-de": "Alemán",
	"lang-name-locale-tr": "Turco",
	"lang-name-locale-vi": "Vietnamita",
	"lang-name-locale-uk": "Ucraniano",
	"lang-name-locale-th": "Tailandés",
	"lang-name-locale-it": "Italiano",
	"lang-name-locale-pl": "Polaco",
	"lang-name-chinese": "Chino (simplificado)",
	"timezone-info": "(UTC+{{@offset}}) {{@country}}",
	"you-started-using-real-wallet": "Usted está usando una cuenta real.",
	"you-started-using-tment-wallet": "Usted está usando una cuenta de concurso.",
	"tournaments": "Concursos",
	"currents": "Actuales",
	"futures": "Próximos",
	"archive": "Archivo",
	"days": "Días",
	"hours": "Horas",
	"minutes": "Minutos",
	"prize-fond": "Premio",
	"participate-price": "Precio de la inscripción",
	"prize-places": "Posiciones más altas",
	"tournament-participants-count": "Participantes",
	"no-tournament-description": "No hay descripción del concurso",
	"utc-info": "(UTC{{@offset}})",
	"begin-time": "Comienza",
	"deductions": "Deducción",
	"reg-in-tournament-for": "Únase al concurso {{@price}}",
	"choose-tournament-to-see-info": "Por favor, seleccione un concurso",
	"has-reged-in-tournament": "Ya se ha registrado",
	"wait-for-reg-in-tournament": "Solicitud de registro enviada",
	"prize-places-low": "{{@count}} posiciones más altas",
	"starting-balance": "Saldo de comienzo",
	"min-deal-size": "Cantidad mínima para operar",
	"max-deal-size": "Cantidad máxima para operar",
	"max-simultaneously-open-deals": "Límite de operación abierta",
	"max-amount-of-open-deals": "Límite de inversión",
	"available-options-types": "Opciones disponibles",
	"tournament-option-type-turbo": "Turbo",
	"tournament-option-type-binary": "Binarios",
	"tournament-option-type-both": "Ambos",
	"tournament-winning-rules": "El trader con el saldo más alto al final de la competencia es el ganador.",
	"available-assets": "Activos disponibles",
	"available-options": "Tipos de transacciones disponibles",
	"greeting": "Bienvenido/a",
	"cashbox-plus-bonus": "+ bonificación {{@value}}",
	"cashbox-input": "Depósito",
	"cashbox-output": "Retiro",
	"bonus-terms-of-use": "Términos de bonificación del usuario",
	"enter-cashbox-input-value": "Ingrese la cantidad a depositar",
	"enter-cashbox-output-value": "Ingrese la cantidad a retirar",
	"do-withdrawal": "Retiro",
	"amount-due": "Importe",
	"will-recieve-to-account": "Obtenga",
	"i-wanna-get-bonus": "Obtenga una bonificación",
	"enter-cashbox-card-type": "Método de pago",
	"finish-time": "Termina",
	"top-users": "Tabla de posiciones",
	"member": "Miembro",
	"balance": "Saldo",
	"prize": "Premio",
	"hint-split-view-button": "Formato",
	"hint-user-profile-button": "Menú del usuario",
	"hint-asset-stat": "Elección de los traders",
	"hint-sound-button": "Sonido",
	"hint-platform-time": "Hora de la plataforma",
	"hint-profitability": "Rentabilidad",
	"hint-payout": "Pago",
	"hint-real-acc": "Cuenta real",
	"hint-demo-acc": "Cuenta de demostración",
	"hint-tournament-acc": "Cuenta de concurso",
	"hint-settings": "Ajustes",
	"hint-support": "Soporte",
	"hint-graph-type": "Tipo de gráfico",
	"hint-candle-interval": "Intervalo de velas",
	"hint-user-lines": "Herramientas gráficas",
	"hint-secondary-lines": "Indicadores",
	"hint-centerize": "Precio actual",
	"hint-zoom-level": "Marco de tiempo",
	"tournament": "Concurso",
	"loading": "Cargando",
	"you-are-in-tournament": "¡Ya está participando!",
	"repeat-tournament": "Recomprar a {{@price}}",
	"unsupported-browser": "El producto se encuentra en fase de prueba, por el momento garantizamos un funcionamiento estable en estos navegadores: Google Chrome, Opera y Yandex Browser. ¡Gracias por su comprensión!",
	"account-is-for-educ": "Esta es solo una cuenta de demostración",
	"participate-in-demo-tments": "Participe en concursos de demostración",
	"use-real-money": "Opere con dinero real",
	"participate-tments-with-real-money": "Participe en concursos y gane premios",
	"native-deal-closed-body": "Opción para {{@assetName}} cerrada a las {{@closeTime}}. La ganancia es {{@incomeValue}}",
	"tournaments-rules": "Reglas del concurso",
	"tournaments-rules-2": "Reglas para participar del concurso.",
	"get-trade-exp": "Obtenga experiencia valiosa de trading",
	"tment-begins-in": "El concurso comienza en",
	"tment-ends-in": "El concurso finaliza en",
	"tment-has-ended": "El concurso ha finalizado",
	"tment-just-ended": "\"{{@name}}\" acaba de finalizar",
	"tment-just-started": "\"{{@name}}\" acaba de comenzar",
	"tment-just-created": "\"{{@name}}\" acaba de crearse",
	"read-more": "Leer más",
	"history-is-empty": "No tiene acuerdos caducados",
	"tournaments-current-is-empty": "No hay concursos activos. Por favor, siga nuestras noticias y nuestros boletines.",
	"tournaments-future-is-empty": "No hay concursos futuros programados. Por favor, siga nuestras noticias y nuestros boletines.",
	"tournaments-ended-is-empty": "No hay concursos finalizados",
	"upper-indicator-line": "Línea indicadora superior",
	"lower-indicator-line": "Línea indicadora inferior",
	"stoch-overbuy-value": "Sobrecomprado",
	"stoch-overbuy-line-width": "Ancho de sobrecomprado",
	"stoch-overbuy-line-color": "Color de sobrecomprado",
	"stoch-oversell-value": "Sobrevendido",
	"stoch-oversell-line-width": "Ancho de sobrevendido",
	"stoch-oversell-line-color": "Color de sobrevendido",
	"de1e3db3-5ed4-4941-aae4-59f3667cc3a3": "Este valor no es válido",
	"889954f14a3839c141bd8d5102094fbb": "Este valor ya está en uso",
	"bd79c0ab-ddba-46cc-a703-a7a4b08de310": "Este valor contiene una dirección de correo electrónico inválida",
	"bf447c1c-0266-4e10-9c6c-573df282e413": "Este valor contiene una dirección de correo electrónico inválida",
	"7da53a8b-56f3-4288-bb3e-ee9ede4ef9a1": "Este valor contiene una dirección de correo electrónico inválida",
	"c1051bb4-d103-4f74-8988-acbcafc7fdc3": "Este campo es obligatorio.",
	"9ff3fdc4-b214-49db-8718-39c315e33d45": "Este valor es demasiado corto. Debe tener {{@min}} caracteres o más.",
	"d94b19cc-114f-4f44-9cc4-4138e80a87b9": "Este valor es demasiado largo. Debe tener {{@limit}} caracteres o menos.",
	"478618a7-95ba-473d-9101-cabd45e49115": "Este valor debe ser igual a {{@compared_value}}.",
	"4dba5f9c79ae34be5884e1a3c8c45e92": "Nombre de usuario o contraseña incorrectos",
	"3e5af93fb888b4aa77301a7603e113d5": "Contraseña incorrecta",
	"2d28afcb-e32e-45fb-a815-01c431a86a69": "Este valor debe ser {{@limit}} o menos",
	"76454e69-502c-46c5-9643-f447d837c4d5": "Este valor debe ser {{@limit}} o superior",
	"ad32d13f-c3d4-423b-909a-857b961eb720": "Este valor no debe estar vacío.",
	"8e179f1b-97aa-4560-a02f-2a8b42e49df7": "El valor que ha seleccionado no es una opción válida.",
	"853ff54c1a66d1a2379e0c46f8eb9ed4": "Requisito inválido {{@name}}",
	"3ac1d32eb3c54e11ef9ea474da816ad6": "Se deben establecer los requisitos {{@name}}",
	"661d3bc6c153e42a3658855010678cbd": "Requisitos desconocidos {{@names}}",
	"51fd5caf0ad30e6acb3a75b8b7f6d060": "No tiene permiso para cambiar el estado de la solicitud procesada",
	"2d2ba82dd886ba3b69da804675842ff5": "Método de pago incorrecto",
	"3c55616c0a7de9c064e6c2d86fa72bc2": "Hora de caducidad inválida",
	"f029308ab5f1672de0b7615c4fa33386": "El activo está cerrado",
	"10cf6f3e2d6a3532b77d924868cbfa62": "El activo está cerrado",
	"64fc8bbac184ae9dab80c8f592d1a6f7": "Ha superado el límite de operación disponible",
	"5561ccf1e94e6b9d88080bdbbcba1821": "Fondos insuficientes",
	"f3a5b44d01097d966072b90187a16ec6": "El usuario no existe",
	"296ea5496bee3177c83ac27a1dc5bb10": "El saldo de concurso debe ser menor al saldo de comienzo",
	"fc53df7c4944ebb53e8b3713126ae226": "El conteo de apuestas abiertas máximas es de {{@limit}}",
	"0f8e85ca21aa2e33752728cf5e843e35": "Ha superado el límite de operación disponible",
	"cbce1334c90e82f44381abe99b98fe5c": "Ha superado el límite del conteo total de opciones abiertas",
	"23bd9dbf-6b9b-41cd-a99e-4844bcf3077f": "Este apodo no está disponible. Por favor elija otro.",
	"promo-ends-in": "La bonificación finaliza en",
	"your-promocode": "Su código promocional",
	"from-value-to-value": "Desde {{@fromValue}} — hasta {{@toValue}}",
	"deposit-sum": "Monto del depósito",
	"bonus-sum": "Bonificación",
	"promos-rules": "Reglas de bonificaciones",
	"promos-rules-2": "Reglas de bonificaciones",
	"participate-promo": "Participe para una bonificación",
	"promo-has-ended": "La bonificación ha finalizado",
	"no-promos-description": "No hay descripción de la bonificación",
	"promos-is-empty": "No hay bonificaciones disponibles",
	"first-launch-disclaimer-content": "¡Cuidado! Solo toma un clic abrir abrir una operación. No requiere confirmación.",
	"accept": "Aceptar",
	"trading-session-closed": "La sesión de trading se ha cerrado",
	"special-offer": "Oferta especial",
	"continue": "Continuar",
	"seconds": "Segundos",
	"trading-sess-starts-in": "La sesión de trading comienza en",
	"trading-session-closed-info-0": "¡Cuidado!",
	"trading-session-closed-info-1": "Los mercados de valores están cerrados los fines de semana.",
	"trading-session-closed-info-2": "Se puede hacer trading en nuestra plataforma desde el lunes a las 3am hasta las 12am del viernes.",
	"trading-session-closed-info-3": "Datos del mercado provistos por Thompson Reuters.",
	"asset": "Activo",
	"additional-info": "Información adicional",
	"fill-profile-to-continue": "Para continuar operando en la plataforma, brinde la información adicional",
	"fill-username-heading": "Querido trader:",
	"fill-username-text": "Para participar en la competencia, introduzca el apodo que lo representará en la lista de participantes de la competencia. Puede cambiarla en cualquier momento en los ajustes de su perfil.",
	"fill-username-placeholder": "Ingrese su apodo",
	"save-and-continue": "Guardar y continuar",
	"profile-name": "Nombre",
	"profile-surname": "Apellido",
	"profile-telephone": "Teléfono",
	"start-trading": "Comenzar a operar",
	"personal-data-safety": "Se garantiza la seguridad de los datos personales",
	"bonus": "Bonificación",
	"new-bonus": "a la cuenta {{@bonus}}",
	"received-bonus": "Junto con el depósito seleccionado, recibirá",
	"received-bonus-value": "una bonificación de: {{@bonus}}",
	"mobile-received-bonus-value": "+ bonificación {{@bonus}}",
	"expires-in": "Caduca en",
	"cannot-buy-option-try-later": "No se puede abrir esta operación, inténtelo de nuevo más tarde.",
	"max-total-bet-limit-exceeded": "Ha superado el importe de operación permitido.\n El importe de operación permitido es de {{@maxBet}}",
	"chart-opens-in": "Abre en:",
	"hint-activate-tment-wallet": "Presione aquí para usar la cuenta de concurso",
	"largest-profit-banner-on-the-asset": "en el activo",
	"largest-profit-banner-button-trade-caption": "Operar",
	"largest-profit-banner-button-trade-caption-2": "Comience a operar con activos.",
	"largest-profit-banner-text": "El mejor momento para operar con un activo",
	"largest-profit-banner-text-2": "El momento óptimo para operar con activos",
	"largest-profit-height-profit": "Rentabilidad aumentada",
	"largest-profit-height-profit-2": "Alta rentabilidad hasta",
	"offer-expires-in": "La oferta caduca en:",
	"offer-expires-in-2": "Tiempo restante hasta el fin de las operaciones:",
	"warning": "Advertencia",
	"banner-tech-works-info-caption": "Actualizaciones técnicas",
	"banner-tech-works-info-content": "Siempre trabajamos para mejorar nuestra plataforma de operaciones.\n Actualmente se está actualizando la plataforma.\n Disculpe las molestias.",
	"confirm-email-content": "Por favor, confirme su dirección de correo electrónico. Haga clic en el botón de abajo para reenviar un correo electrónico con un enlace de confirmación.",
	"confirm-email-caption": "Reactivación de la cuenta",
	"reload": "Volver a cargar",
	"resend-confirmation": "Volver a enviar",
	"resend-confirmation-again": "Intentar de nuevo",
	"confirmation-mail-sent": "Enviado",
	"banner-not-enough-funds-for-tment": "No tiene fondos suficientes en su cuenta. Recargue su cuenta para participar en el concurso.",
	"tment-reenter-not-allowed": "No puede realizar compras adicionales mientras haya transacciones abiertas.",
	"fill-profile-wrong-phone": "Número de teléfono inválido",
	"fill-profile-wrong-name": "Nombre inválido",
	"fill-profile-wrong-surname": "Apellido inválido",
	"fill-user-wrong-promocode": "Código promocional inválido",
	"wrong-promocode-max-sum": "Monto máximo de depósito {{@sum}}",
	"wrong-promocode-min-sum": "Monto mínimo {{@sum}}",
	"wrong-withdrawal-min-sum": "Monto mínimo {{@sum}}",
	"wrong-withdrawal-max-sum": "Monto máximo de retiro {{@sum}}",
	"wrong-promocode-expired": "Expirado",
	"wrong-promocode-only-for-second-deposit": "Disponible solo a partir del segundo depósito",
	"wrong-promocode-only-for-first-deposit": "Disponible solo para el primer depósito",
	"wrong-promocode-used": "El código promocional ya ha sido utilizado",
	"fill-user-wrong-phone": "Número de teléfono inválido",
	"fill-user-wrong-card": "Número de tarjeta inválido",
	"fill-user-wrong-customer_purse": "Número de cuenta inválida",
	"fill-user-wrong-name": "Nombre inválido",
	"fill-user-wrong-surname": "Apellido inválido",
	"please-rotate-device": "Turn the device over so that you can easily use the terminal.",
	"swipe-up-to-enter-fs": "Deslice hacia arriba para el modo de pantalla completa",
	"click-to-enter-fs": "Toque en cualquier lugar de la pantalla para cambiar a la pantalla completa",
	"reconnect": "Reconectar",
	"reconnected": "¡Reconectado!",
	"free-reg": "Registro gratis",
	"investments": "Operaciones",
	"buy-time": "Tiempo de compra",
	"total-investment": "Inversión total",
	"total-income": "Pago total",
	"result": "Resultado",
	"ur-income-would-be": "Su ganancia",
	"create-account-for-free": "Cree una cuenta gratis",
	"resume-use-demo": "Continuar en el modo de demostración",
	"reg-request-message": "Si usted hubiera operado en nuestro sitio web, ya podría haber ganado {{@ingresos}}. No pierda más tiempo, ¡empiece a operar!",
	"trade-without-restrictions": "Opere sin restricciones",
	"trade-without-restrictions-message": "Si desea abrir más de 5 operaciones a la vez, abra una cuenta real de operaciones y opere sin límites. Para seguir usando la cuenta de demostración, espere a que sus acuerdos actuales caduquen.",
	"use-real-wallet": "Cuenta real",
	"support": "Soporte",
	"search-asset": "Buscar un activo",
	"error-sending-email-confirmation": "Se ha producido un error al enviar el correo. Por favor, inténtelo de nuevo más tarde.",
	"error-sending-email-confirmation-with-time": "Podemos enviarle un nuevo correo electrónico en {{@time}} minutos. Para activar su cuenta, consulte su correo electrónico o póngase en contacto con nuestro Soporte.",
	"risk-free-trades": "Operaciones sin riesgos",
	"count-trades-for-bet": "{{@count}} operaciones para {{@sum}}",
	"count-x-bet": "{{@count}}×{{@bet}}",
	"White": "Blanco",
	"Red": "Rojo",
	"Pink": "Rosa",
	"Purple": "Violeta",
	"Deep Purple": "Púrpura",
	"Indigo": "Índigo",
	"Blue": "Azul",
	"Cyan": "Cian",
	"Green": "Verde",
	"Light Green": "Verde claro",
	"Lime": "Verde lima",
	"Yellow": "Amarillo",
	"Amber": "Ámbar",
	"Orange": "Naranja",
	"activate-tournament-wallet": "Activar monedero de concurso",
	"deposit-using-agreements-header": "Artículos de bonificación",
	"deposit-using-agreements-p1": "Una bonificación son fondos adicionales que la empresa proporciona para aumentar el potencial de trading de los inversores.",
	"deposit-using-agreements-p2": "Al hacer un depósito, una cierta cantidad de dinero de bonificación puede ser acreditada a su cuenta, el tamaño de la bonificación depende del tamaño de su depósito.",
	"deposit-using-agreements-p3": "La bonificación no limita los fondos que puede retirar: puede retirar sus ganancias junto con el importe de su depósito en cualquier momento. Tenga en cuenta que, al retirar fondos, se asignará el estado inactivo a todos los fondos de bonificación aún no obtenidos, y se debitarán de su cuenta.",
	"choose-payment-method": "Elija un método de pago",
	"choose-payment-sum": "Seleccione la cantidad de depósito",
	"plus-value-bonus": "Bonificación de + {{@value}}",
	"deposit-user-sum-value-caption": "¿Quiere elegir su propio importe? Utilice el campo de entrada",
	"i-have-promocode": "Tengo un código promocional",
	"requisiste-name-phone": "Teléfono",
	"no-bonus": "sin bonificaciones",
	"refresh": "Refrescar",
	"browser": "Navegador",
	"make-a-deposit": "Hacer un depósito",
	"cashbox-withdrawal-info-0-header": "¿Cómo puedo retirar fondos de mi cuenta?",
	"cashbox-withdrawal-info-0-content": "Las opciones disponibles son: tarjeta bancaria o monederos electrónicos Qiwi/Yandex Money/WebMoney. Los dueños de microcuentas pueden tener solo una aplicación activa para el retiro de fondos.",
	"cashbox-withdrawal-info-1-header": "¿Cuál es el importe mínimo de dinero que se puede retirar de la cuenta?",
	"cashbox-withdrawal-info-1-content": "Importe mínimo de retiro: ₽300 o $5 o €5. Importe máximo de retiro para una única transacción: ₽15.000 o $200 o €200.",
	"cashbox-withdrawal-info-2-header": "¿Cómo retiro un importe mayor a ₽15.000 o $200 o €200?",
	"cashbox-withdrawal-info-2-content": "Esta restricción tiene como fin evitar retiros rápidos de las cuentas. Los importes que superan el límite establecido solo podrán retirarse durante un período de tiempo mayor. Si necesita retirar un importe mayor, puede dividir sus retiros en importes de ₽15.000 o $200 o €200. No hay límite en la cantidad de solicitudes de retiro que puede hacer. Si quisiera un retiro por un monto mayor en un único pago, por favor contacte al equipo de soporte de la plataforma. Si su cuenta no está verificada, podría tomar hasta 3 días hábiles procesar su solicitud de retiro de fondos. No puede enviar más de una solicitud de retiro de fondos por día.",
	"cashbox-withdrawal-info-3-header": "¿Qué tan rápido se ejecuta el retiro de fondos?",
	"cashbox-withdrawal-info-3-content-a": "Procesar una solicitud toma una hora, asumiendo que la solicitud se envíe en el horario de trabajo del departamento financiero de la plataforma y que su cuenta haya sido verificada de acuerdo con los requisitos de la plataforma. ",
	"cashbox-withdrawal-info-3-content-b": "El horario de trabajo del departamento financiero es de lunes a viernes de 10:00 a 22:00 (GMT +2). Si envía una solicitud de retiro de fondos por fuera del horario de trabajo del departamento financiero o en un día festivo no laborable, entonces su solicitud se procesará al inicio del siguiente día laborable. Si su cuenta no ha sido verificada, entonces su solicitud de retiro de fondos se procesará en un plazo de tres días hábiles. No puede enviar más de una solicitud de retiro de fondos por día.",
	"cashbox-withdrawal-info-4-header": "Política de retiro",
	"cashbox-withdrawal-info-4-content-a": "The client must indicate all of the requested data in the \"Profile Settings\" section in order to ensure that their request is duly processed. If it is determined that inaccurate or incomplete data was entered, your funds withdrawal request may be rejected or delayed.",
	"cashbox-withdrawal-info-4-content-b": "Funds are withdrawn to the same bank account (or the same payment system) that was used to fund your account. If it is not possible to complete the transaction, then you should contact the support service by either initiating an online chat or sending a support request to support@binarium.com.",
	"cashbox-withdrawal-info-5-header": "Do I need to provide documents when I withdraw funds? If I do, then which ones?",
	"cashbox-withdrawal-info-5-content-a": "Please provide all of your personal data in the \"Profile Settings\" section in order to ensure rapid withdrawals. If you use several bank cards or the payment details do not match the ones that you provided during registration, you will need to undergo a full authorization process and prove that the cards actually belong to you. Funds may not be withdrawn to third-party accounts. ",
	"cashbox-withdrawal-info-5-content-b": "To complete the verification process, please send a scan of your passport and the front side of your bank card to support@binarium.com so that the first and last names of the owner can be seen. If you own not an embossed card, then you must send a scan of your bank statement displaying a transaction from this card to your Binarium account in addition to the copy of your passport. The company reserves the right to require additional supporting documents if the cardholder and trading account data do not match.",
	"cashbox-withdrawal-info-6-header": "¿Cuáles son las condiciones para retirar los fondos de bonificación?",
	"cashbox-withdrawal-info-6-content-a": "The bonus itself may not be withdrawn immediately after it has been accrued. The broker credits this money to your account as a bonus to increase your trading opportunities. The interest that you earn using the bonus funds also constitutes a bonus, and it is available for withdrawal only after the necessary trade turnover is achieved. In order to withdraw the bonus itself, you need to achieve a x40 turnover of the bonus amount in the account. If you were given a no deposit bonus, then the leverage is increased to 50, that is, the turnover on the account should be equal to the bonus x50 and the maximum withdrawal amount may not exceed the amount of the no deposit bonus that has been added. Cash prizes that are won in the company's free contests are considered bonuses that are only available for withdrawal after achieving a x40 turnover.",
	"cashbox-withdrawal-info-6-content-b": "Example. When you made a deposit, you accrued $150 as a bonus. According to the rules, you need to achieve a total value of purchased options of 30 x 150 = $4,500. After this value is achieved, you can withdraw the bonus funds. In this case, both profitable and unprofitable transactions are taken into account. Prematurely terminated transactions are not included in the turnover. There are no restrictions on the withdrawal of profits.",
	"cashbox-withdrawal-info-6-content-c": "Si va a retirar la parte del depósito, la bonificación se deducirá automáticamente de su cuenta.",
	"cashbox-withdrawal-info-6-content-d": "If you have any questions, then please contact the Binarium support service.",
	"cashbox-withdrawal-info-7-header": "I am not able to create a funds withdrawal request for my account. What could be wrong?",
	"cashbox-withdrawal-info-7-content": "First, check whether all of your personal information is listed on your profile page in the \"Profile\" section. Once again, make sure that you entered all the information correctly at the time that you submit your request. Special characters like +, -, / etc are invalid. If all of the entered information is correct, but the problem persists, please contact our customer support service via online chat or at support@binarium.com.",
	"deposit-info-1": "Una bonificación son fondos adicionales que la empresa proporciona para aumentar el potencial de trading de los traders",
	"deposit-info-2": "Al hacer un depósito, una cierta cantidad de dinero de bonificación puede ser acreditada a su cuenta, el tamaño de la bonificación depende del tamaño de su depósito.",
	"deposit-info-3": "The bonus does not limit the amount of funds that you can withdraw: you can withdraw your profits at any time as well as the amount of your deposit. Please note that when withdrawing funds, all bonus funds that were not used in trades with a x40 turnover will be assigned inactive status and will be debited from your account.",
	"withdrawal-heading": "Your request will be processed within 24 hours from the time when you submit it.",
	"withdrawal-content": "Si la solicitud se emitió fuera de las horas de trabajo del departamento financiero de la empresa, se procesará en el próximo día laborable.",
	"withdrawal-restricted-heading": "Se ha superado el límite de solicitud de retiro de fondos",
	"withdrawal-restricted-content": "Unfortunately, we cannot accept more than five requests per day. To submit a new request, cancel the requests that you previously submitted or try again in 24 hours",
	"withdrawal-amount-caption": "Importe de pago",
	"withdrawal-type-caption": "Método de retiro de fondos",
	"withdrawal-button-caption": "Retirar fondos",
	"requisite-name-card": "Número de tarjeta",
	"requisite-name-phone": "Teléfono",
	"requisite-name-customer_purse": "Monedero del cliente",
	"withdrawal-request-sent": "La solicitud se ha puesto en cola",
	"withdrawal-request-sent-extra-info": "You can track the request status in the “Transaction History” section.",
	"withdrawal-method-qiwi_ecom": "Qiwi",
	"withdrawal-method-qiwi": "Qiwi",
	"withdrawal-method-yandex_money_ecom": "Yandex Money",
	"withdrawal-method-webmoney_1gp": "WebMoney",
	"withdrawal-method-card": "Visa/Mastercard",
	"videohub": "Educación",
	"asset-type-all": "Todos",
	"asset-type-currency": "Moneda",
	"asset-type-crypto": "Cripto",
	"asset-type-goods": "Bienes",
	"cashbox-withdrawal-info": "It will take some time to process a request. Usually it takes up to 24 hours for the finance department to review request during business hours. We are happy to report that we do not freeze your balance while you wait for the withdrawal request to be approved. That way, you can continue trading.",
	"expiration-caption-16": "En 24 horas",
	"expiration-caption-15": "Al finalizar el día",
	"trends": "Tendencias",
	"show-chart": "Mostrar gráfico",
	"hide-chart": "Ocultar gráfico",
	"trend-active": "Activas",
	"trend-non-active": "Todos",
	"trends-is-empty": "Las tendencias se están actualizando",
	"what-are-trends": "¿Qué son las tendencias?",
	"what-are-trends-advice-content": "Trends are a special trading tool that allow you to quickly find an asset with profitable potential (with a pronounced price direction) and to open a trade in the direction of the trend.",
	"not-enough-money-for-trends-detailed": "A unique trading tool from Binarium is available for customers with a real balance over {{@balance}}. Promising opportunities:",
	"get-access-to-trends": "Acceda a las tendencias",
	"trends-features-one": "Track all asset trends on the market",
	"trends-features-two": "Instantly open trades in the direction of the trend when it appears",
	"month-0": "Ene",
	"month-1": "Feb",
	"month-2": "Mar",
	"month-3": "Abr",
	"month-4": "May",
	"month-5": "Jun",
	"month-6": "Jul",
	"month-7": "Ago",
	"month-8": "Set",
	"month-9": "Oct",
	"month-10": "Nov",
	"month-11": "Dic",
	"day-0": "Lun",
	"day-1": "Mar",
	"day-2": "Mié",
	"day-3": "Jue",
	"day-4": "Vie",
	"day-5": "Sáb",
	"day-6": "Dom",
	"trading-room": "Salón de trading",
	"trading-room-entering-time": "Hora de ingreso",
	"trading-room-expiration": "Caducidad",
	"trading-room-strength": "Fuerza",
	"trading-room-strike-price": "Precio de ejercicio",
	"demo-stats-banner-header-caption": "¡Excelente!",
	"demo-stats-banner-header-caption-2": "Congratulations!",
	"demo-stats-banner-you-earned-on-demo": "You've earned money in a demo account.",
	"demo-stats-banner-total-deals-amount": "Operaciones totales",
	"demo-stats-banner-successfull-deals-percentage": "Porcentaje de operaciones exitosas",
	"demo-stats-banner-real-account-opening-request": "Abra una cuenta real y podrá retirar los ingresos que ganó",
	"demo-stats-banner-open-real-account-button-caption": "Abrir una cuenta real",
	"demo-stats-banner-keep-trading-on-demo": "Continuar operando con la cuenta de demostración",
	"demo-stats-banner-you-have-done": "Ha efectuado",
	"demo-stats-banner-you-have-trades-closed-in-a-row": "operaciones seguidas",
	"demo-stats-banner-you-have-trades-closed-in-a-row-successfully": "operaciones rentables seguidas",
	"demo-stats-banner-earning-on-demo-account": "Ganancias en su cuenta de demostración",
	"demo-stats-banner-closed-in-a-row-2": "successful transactions",
	"tour-next-button-caption": "Continuar",
	"tour-reading-duration-caption": "Lectura de 4 minutos.",
	"tour-slides-steps-count": "Paso {{@currentSlide}} de {{@totalSlidesCount}}",
	"tour-slide-0-caption": "Bienvenido a la plataforma de trading Binarium",
	"tour-slide-0-content": "Esta breve demostración le presentará los principios básicos del trading y la interfaz de la plataforma Binarium.",
	"tour-slide-0-content-1": "Lea todo para aprender a operar más eficazmente en la plataforma.",
	"tour-slide-0-content-2": "Esta breve demostración le presentará los principios básicos del trading y la interfaz de la plataforma Binarium.",
	"tour-slide-0-content-3": "The main menu is on the left. For example, you can refill your account in the <span class=\"bold\">Bank</span> section. And you can order trades using the best traders on the platform in the <span class=\"bold\">Trading room</span> section!",
	"tour-slide-0-extra-info": "Lea todo para aprender a operar más eficazmente en la plataforma.",
	"tour-slide-1-caption": "¿Cómo se hace dinero en la plataforma?",
	"tour-slide-1-content": "<span class=\"bold\">La plataforma de trading le permite realizar operaciones </span> a partir inversiones a corto plazo en activos financieros: pares de divisas, criptomonedas, materias primas y otros instrumentos financieros.",
	"tour-slide-2-caption": "¿Cuál es el principio básico detrás de una operación?",
	"tour-slide-2-content-a": "<span class=\"bold\">Una operación es una predicción de cómo cambiará el precio de un activo financiero</span> a lo largo de un período de tiempo determinado. Los inversores realizan operaciones <span class=\"green\">a largo plazo</span> o a <span class=\"red\">corto plazo</span>.",
	"tour-slide-2-content-b": "Si su predicción resulta ser cierta, recibirá ingresos. Si se equivoca, entonces perderá todos los fondos que ha invertido.",
	"tour-slide-3-caption": "¿Cómo se hacen operaciones en la plataforma Binarium?",
	"tour-slide-3-content": "<span class=\"bold\">Seleccione un activo </span> cuya tendencia de precio quiera predecir.",
	"tour-slide-4-caption": "¿Cómo se hacen operaciones en la plataforma Binarium?",
	"tour-slide-4-content": "<span class=\"bold\">Seleccione el tamaño de su inversión.</span>",
	"tour-slide-5-caption": "¿Cómo se hacen operaciones en la plataforma Binarium?",
	"tour-slide-5-content": "<span class=\"bold\">Abra una operación</span> y haga una predicción sobre que el precio va a <span class=\"green\">aumentar</span> o<span class=\"red\">disminuir</span>. Espere a que la operación se cierre.",
	"tour-slide-6-caption": "¡Buena suerte con sus operaciones en la plataforma Binarium!",
	"tour-slide-6-additional-caption": "Si su predicción fue correcta, sus ganancias serán automáticamente acreditadas a su cuenta de trading.",
	"tour-slide-6-a-trading-rules": "Condiciones de trading",
	"tour-slide-6-a-card-0-caption": "La cantidad de ingresos que usted recibirá al hacer una predicción exitosa:",
	"tour-slide-6-a-card-0-content": "<span class=\"big\">Hasta un 90%</span> del monto de su inversión",
	"tour-slide-6-a-card-1-caption": "Depósito mínimo para operar:",
	"tour-slide-6-a-card-1-content": "<span class=\"big\">{{@minWithdrawal}}</span>",
	"tour-slide-6-a-card-2-caption": "Tiempo promedio necesario para retirar fondos:",
	"tour-slide-6-a-card-2-content": "<span class=\"big\">30</span> minutos",
	"tour-slide-6-a-card-3-caption": "Deposite fondos en una cuenta real para comenzar a operar:",
	"tour-slide-6-a-card-3-button-caption": "Deposite fondos y comience a operar",
	"tour-slide-6-a-dont-show-again": "Ignorar la visita introductoria a la plataforma",
	"tour-slide-6-b-trading-rules": "Condiciones de trading",
	"tour-slide-6-b-card-0-caption": "La cantidad de ingresos que usted recibirá al hacer una predicción exitosa:",
	"tour-slide-6-b-card-0-content": "<span class=\"big\">Hasta un 90%</span> del monto de su inversión.",
	"tour-slide-6-b-card-1-caption": "depósito mínimo para operar.",
	"tour-slide-6-b-card-1-content": "<span class=\"big\">{{@minWithdrawal}}</span>",
	"tour-slide-6-b-card-2-caption": "tiempo promedio necesario para retirar fondos.",
	"tour-slide-6-b-card-2-content": "<span class=\"big\">30</span> minutos",
	"tour-slide-6-b-card-3-caption": "Aprenda cómo operar sin riesgos, usando una cuenta de demostración",
	"tour-slide-6-b-card-3-button-caption": "Opere con una cuenta de demostración",
	"tour-slide-6-b-dont-show-again": "Ignorar la visita introductoria a la plataforma",
	"user-terms-caption": "Opere con un clic",
	"what-is-trading-room": "¿Qué es un salón de trading?",
	"what-is-trading-room-advice-content": "A trading room is a handy tool that allows you to copy the transactions of the best traders of the platform in one click. You can increase the efficiency of your trades and save time thanks to this tool.",
	"not-enough-money-for-trading-room-detailed": "Trade and earn money with the best traders on the Binarium platform using the trading room. Top up your real balance to {{@minBalance}} and receive the following benefits:",
	"get-access-to-trading-room": "Access to the trading room",
	"have-access-to-trading-room": "Para acceder al \"Salón de Trading\", contacte a su administrador o al Soporte.",
	"trading-room-features-one": "Esté atento a las transacciones del trader más exitoso de la plataforma",
	"trading-room-features-two": "Copie transacciones y obtenga ganancias",
	"trading-room_1-title": "Trade together",
	"trading-room_1-text": "Keep an eye out for transactions of the most successful trader of the platform.",
	"trading-room_2-title": "Take advantage of others' successful experience",
	"trading-room_2-text": "Copy the behavior of other traders and make a profit!",
	"trading-room_refill": "To access the \"Trading room\", refill your balance to",
	"account_level": "Account level",
	"modal-confirm_title": "Confirm your e-mail address",
	"modal-confirm_text-1": "The confirmation link in the message that you received after registration:",
	"modal-confirm_text-2": "Did you fail to receive a message with a confirmation link? Please check your \"Spam\" folder. Sometimes messages end up there. Or request the message again:",
	"modal-confirm_button": "Send the message again",
	"modal-confirm_error-1-1": "A new e-mail can be sent to you in {{@time}} minutes. To activate your account, please check your email or contact our support service or",
	"modal-confirm_error-1-2": "contact the support service.",
	"modal-confirm_support": "Contact the support service",
	"timer_days": "Days",
	"timer_hours": "Hours",
	"timer_minutes": "Minutes",
	"timer_seconds": "Seconds",
	"tournament_button": "Participate in the contest",
	"modal-oneclick_title": "Trade in one click",
	"modal-oneclick_text": "Please note that you can open trades on the platform in just one click. There is no additional confirmation.",
	"modal-oneclick_button": "Accept and continue",
	"modal-tbalance_title": "Refill your account",
	"modal-tbalance_text": "You do not have sufficient funds in the account. Please refill your account in order to participate in the contest.",
	"modal-tbalance_button": "Make a deposit",
	"modal-tech_title": "We will return soon!",
	"modal-tech_text-1": "We constantly work to improve our trading platform. At the moment we are performing updates. We are sorry for any inconvenience that we may cause you.",
	"modal-tech_text-2": "Time remaining until the end of work:",
	"modal-tech_button": "Continue",
	"modal-session_title": "Pay attention",
	"modal-session_text-1": "Stock markets are closed on the weekend.",
	"modal-session_text-2": "The trading platform is accessible",
	"modal-session_text-3": "between 3:00 AM on Monday and 12:00 AM on Friday.",
	"modal-session_text-4": "You trading session will begin in:",
	"modal-session_button": "Continue",
	"modal-tn_title": "Welcome to",
	"modal-tn_text-1": "The trader with the highest balance at the end of the contest is the winner.",
	"modal-tn_text-2": "Available assets:",
	"modal-tn_text-3": "Available types of transactions:",
	"modal-tn_button": "Start",
	"modal-nickname_title": "Select a nickname",
	"modal-nickname_text": "To participate in the contest, enter the nickname that will represent you in the list of contest participants. You can change it at any time in your profile settings.",
	"modal-nickname_button": "Save and continue",
	"modal-profile_title": "Additional information",
	"modal-profile_text": "Please provide additional information to continue working on the platform.",
	"modal-profile_name": "First name",
	"modal-profile_surname": "Last name",
	"modal-profile_phone": "Phone number with code",
	"modal-profile_button": "Start trading",
	"modal-profile_aside": "The safety of your personal data is guaranteed.",
	"form-error_required": "This field is required.",
	"form-error_name-short": "The name is too short.",
	"form-error_name-format": "Invalid name format",
	"form-error_surname-short": "The last name is too short.",
	"form-error_surname-format": "Invalid last name format.",
	"form-error_phone-format": "Invalid phone number format"
}